{
  "GroupId": 204,
  "translator": "螢@碧蓝档案资讯站",
  "content": [
    {
      "TextJp": "太古の教義",
      "TextCn": "太古的教义",
      "TextKr": "",
      "TextEn": "Ancient Doctrines",
      "TextTh": "ความรู้โบราณ",
      "TextTw": "太古的教義",
      "GroupId": 204,
      "SelectionGroup": 0,
      "BGMId": 999,
      "Sound": "",
      "Transition": 0,
      "BGName": 4219378494,
      "BGEffect": 0,
      "PopupFileName": "",
      "ScriptKr": "#title;고대의 교의",
      "VoiceJp": ""
    },
    {
      "TextJp": "",
      "TextCn": "",
      "TextKr": "",
      "TextEn": "",
      "TextTh": "",
      "TextTw": "",
      "GroupId": 204,
      "SelectionGroup": 0,
      "BGMId": 0,
      "Sound": "SE_FootStep_02",
      "Transition": 0,
      "BGName": 0,
      "BGEffect": 0,
      "PopupFileName": "",
      "ScriptKr": "#wait;2000",
      "VoiceJp": ""
    },
    {
      "TextJp": "",
      "TextCn": "",
      "TextKr": "",
      "TextEn": "",
      "TextTh": "",
      "TextTw": "",
      "GroupId": 204,
      "SelectionGroup": 0,
      "BGMId": 0,
      "Sound": "",
      "Transition": 0,
      "BGName": 0,
      "BGEffect": 0,
      "PopupFileName": "",
      "ScriptKr": "4;마에스트로;00\n#4;a\n#wait;1000",
      "VoiceJp": ""
    },
    {
      "TextJp": "",
      "TextCn": "",
      "TextKr": "",
      "TextEn": "",
      "TextTh": "",
      "TextTw": "",
      "GroupId": 204,
      "SelectionGroup": 0,
      "BGMId": 0,
      "Sound": "SE_Clatter_02",
      "Transition": 0,
      "BGName": 0,
      "BGEffect": 0,
      "PopupFileName": "",
      "ScriptKr": "4;마에스트로;00\n#4;stiff\n#wait;2500",
      "VoiceJp": ""
    },
    {
      "TextJp": "いわゆる「崇高」というものは、二つの側面を持っている……ひとつは、到底たどり着くことの叶わない「神秘」。そしてもうひとつは、不可逆の「恐怖」。",
      "TextCn": "所谓“崇高”，总是具有不同的两面……\n一面是永远无法抵达的“神秘”，而另一面则是不可逆转的“恐怖”。",
      "TextKr": "",
      "TextEn": "There are two sides to the sublime. If unfathomable Mystic lies on one side, then irreversible Terror must dwell on the other.",
      "TextTh": "ความสูงส่งนั้นมีสองด้าน หากด้านหนึ่งมีความลึกลับที่ไม่อาจแตะต้องได้อยู่ล่ะก็#nอีกด้านหนึ่งก็คือความกลัวที่ไม่สามารถหวนคืนได้",
      "TextTw": "所謂的「崇高」擁有不同的兩面……#n一是終究無法抵達的「神秘」；而另一面是無法逆轉的「恐怖」。",
      "GroupId": 204,
      "SelectionGroup": 0,
      "BGMId": 73,
      "Sound": "",
      "Transition": 0,
      "BGName": 0,
      "BGEffect": 0,
      "PopupFileName": "",
      "ScriptKr": "4;마에스트로;00;숭고(the sublime)는 두 개의 양면성을 지니고 있다.#n한쪽에 감히 와 닿을 수 없는 신비가 있다면, 그 반대편엔 돌이킬 수 없는 공포가 자리하고 있지.",
      "VoiceJp": "",
      "Unsure": false
    },
    {
      "TextJp": "例えるならばそう、それはまるでコインの両面のように、「神秘」と「恐怖」とは互いに切り離すことができないものなのだ。",
      "TextCn": "举例来说，就如硬币总有两面一般，「神秘」和「恐怖」是不可分割的。",
      "TextKr": "",
      "TextEn": "Like two sides of a coin, Terror and Mystic are inseparable.",
      "TextTh": "เช่นเดียวกับเหรียญที่มีสองด้าน ความกลัวกับความลึกลับ#nก็คือสิ่งเดียวกันที่ไม่สามารถแยกออกจากกันได้",
      "TextTw": "舉例來說，如同硬幣的兩面一般，「神秘」和「恐怖」是無法分離彼此的。",
      "GroupId": 204,
      "SelectionGroup": 0,
      "BGMId": 0,
      "Sound": "",
      "Transition": 0,
      "BGName": 0,
      "BGEffect": 0,
      "PopupFileName": "",
      "ScriptKr": "4;마에스트로;00;동전의 양면처럼, 공포와 신비는 따로 떼어낼 수 없는 한 몸이라고 볼 수 있는 것이다.",
      "VoiceJp": ""
    },
    {
      "TextJp": "しかし宙に投げられたコインが最終的にはどちらか一方の面を見せるのと同じように、「崇高」もまたそのような形で顕現する。",
      "TextCn": "然而正如向空中抛出的硬币最终只会展示其中一面，“崇高”也会以类似形式显现。",
      "TextKr": "",
      "TextEn": "However, just as a tossed coin will only show one side of itself at any given moment, the sublime can only manifest itself in one way at a time.",
      "TextTh": "แต่ว่าเช่นเดียวกับเหรียญที่โยนขึ้นไป พอตกลงมามันก็จะเห็นแค่เพียงด้านเดียวเท่านั้น#nความสูงส่งเองก็ปรากฎให้เราเห็นในลักษณะนั้นเช่นกัน",
      "TextTw": "然而與丟向天空的硬幣終究會展現其中一面相同，「崇高」也會以類似的形式顯現。",
      "GroupId": 204,
      "SelectionGroup": 0,
      "BGMId": 0,
      "Sound": "",
      "Transition": 0,
      "BGName": 0,
      "BGEffect": 0,
      "PopupFileName": "",
      "ScriptKr": "4;마에스트로;00;하지만 던져진 동전이 언제나 단 하나의 정황만 보여주듯, 숭고 또한 그런 식으로만 우리들의 세계에 현현한다.",
      "VoiceJp": ""
    },
    {
      "TextJp": "「神秘」、そして「恐怖」。これらの本質は同じだが、私たちは「崇高」の形として、その二つの内の一面しか観測することができない。",
      "TextCn": "“神秘”，以及“恐怖”。尽管二者本质相同，我们却只能观测两面中名为“崇高”的一面。",
      "TextKr": "",
      "TextEn": "Terror or Mystic. The essence of the two is the same, but we can only observe one aspect at a time.",
      "TextTh": "ความกลัว หรือความลึกลับ..... แก่นแท้ของทั้งสองอย่างคือสิ่งเดียวกัน#nแต่เรามักจะเห็นความสูงส่งเพียงแค่แง่มุมเดียวเท่านั้น",
      "TextTw": "「神秘」以及「恐怖」。儘管兩者的本質相同，我們卻只能觀測到「崇高」的其中一個樣貌。",
      "GroupId": 204,
      "SelectionGroup": 0,
      "BGMId": 0,
      "Sound": "SE_FootStep_03c",
      "Transition": 0,
      "BGName": 0,
      "BGEffect": 0,
      "PopupFileName": "",
      "ScriptKr": "4;마에스트로;00;공포, 혹은 신비. 둘의 본질은 같지만, 우리는 숭고의 단 하나의 모습만을 관측할 수 있는 것이지.\n#4;m3",
      "VoiceJp": "",
      "Unsure": false
    },
    {
      "TextJp": "と、まあ語ってはみたものの……お恥ずかしい話だが実のところ、私たちはそれを真に理解できていたわけではなかった。つまり[ruby=ゲマトリア]私たち[/ruby]は、失敗したのだ。",
      "TextCn": "话虽如此……说来惭愧，实际上我们也没能完全理解它。#n总之，[ruby=数秘术]我们[/ruby]失败了。",
      "TextKr": "",
      "TextEn": "And the sublime...was not something we could understand. Simply put, We, Gematria, failed.",
      "TextTh": "อีกทั้งความสูงส่งนั้น... ไม่ใช่สิ่งที่เราจะเข้าใจได้ หรือก็คือ...[ruby=เกมาเทรีย]พวกเรา[/ruby]ล้มเหลว",
      "TextTw": "話雖如此……儘管羞恥但事實上，我們也尚未完全理解它。#n換句話說，[ruby=蓋瑪特利亞]我們[/ruby]失敗了。",
      "GroupId": 204,
      "SelectionGroup": 0,
      "BGMId": 0,
      "Sound": "SE_Clatter_01",
      "Transition": 0,
      "BGName": 0,
      "BGEffect": 0,
      "PopupFileName": "",
      "ScriptKr": "4;마에스트로;00;그리고 그 숭고는…… 우리가 이해할 수 있는 것은 아니었다.#n말하자[ruby=게마트리아]면 우리는 [/ruby]실패했다.\n#4;stiff",
      "VoiceJp": ""
    },
    {
      "TextJp": "私たちは「神秘」を手にすることはできず、それどころか真っ当に手が届くことすらなかった。",
      "TextCn": "我们不仅无法获得“神秘”，甚至无法真正触及它。 ",
      "TextKr": "",
      "TextEn": "We were unable to reach the essence of Mystic, let alone take it within our grasp. ",
      "TextTh": "พวกเราไม่สามารถเข้าถึงความลึกลับ และไม่สามารถครอบครองมันได้เช่นกัน",
      "TextTw": "我們沒能獲得「神秘」，甚至連真正觸及它都做不到。 ",
      "GroupId": 204,
      "SelectionGroup": 0,
      "BGMId": 0,
      "Sound": "",
      "Transition": 0,
      "BGName": 0,
      "BGEffect": 0,
      "PopupFileName": "",
      "ScriptKr": "4;마에스트로;00;우리는 신비에 가 닿을 수 없고, 그것을 소유하지도 못했다. ",
      "VoiceJp": ""
    },
    {
      "TextJp": "",
      "TextCn": "",
      "TextKr": "",
      "TextEn": "",
      "TextTh": "",
      "TextTw": "",
      "GroupId": 204,
      "SelectionGroup": 0,
      "BGMId": 0,
      "Sound": "",
      "Transition": 2482233134,
      "BGName": 1047754314,
      "BGEffect": 0,
      "PopupFileName": "",
      "ScriptKr": "#all;hide",
      "VoiceJp": ""
    },
    {
      "TextJp": "私たちが近づくことができたのは「恐怖」だけであり、その上それは[ruby=ミメシス]複製[/ruby]されたものに過ぎなかったのだ。",
      "TextCn": "我们能接近的，只不过是[ruby=Mimesis]摹仿[/ruby]出来的“恐怖”。",
      "TextKr": "",
      "TextEn": "All that we could manage was Terror, and that too was but a Mimesis.",
      "TextTh": "สิ่งที่พวกเราเข้าถึงได้มีเพียงความกลัวเท่านั้น และมันก็เป็นเพียงแค่การเลียนแบบ#n[ruby=มิเมซิส]ที่ถูกเลียนแบบซ้ำ[/ruby]ขึ้นมาอีกครั้ง",
      "TextTw": "我們能接近的只有「恐怖」而已，並且那也只不過是[ruby=Mimesis]複製[/ruby]出來的東西罷了。",
      "GroupId": 204,
      "SelectionGroup": 0,
      "BGMId": 0,
      "Sound": "",
      "Transition": 0,
      "BGName": 0,
      "BGEffect": 0,
      "PopupFileName": "",
      "ScriptKr": "#na;마에스트로;우리가 접근할 수 있었던 것은 그저 공포 뿐이였으며, 그것 또[ruby=미메시스]한 복제된 [/ruby]재현품일 뿐이었다.",
      "VoiceJp": ""
    },
    {
      "TextJp": "まあシミュラクラの概念を支持する私としては、「原本」や「複製」といった区分は無意味だと考えているものの……。",
      "TextCn": "虽然对于支持[tooltip=simulacrum。让·鲍德里亚在《拟像与仿真》一书中提出的理论。拟像论认为世界已经由没有根基的符号和拟像所构成，使“真实”与“非真实”之间的区别已经没有意义。]拟像论[/tooltip]的我来说，区分“原件”和“复制”并无意义……",
      "TextKr": "",
      "TextEn": "However, I am a supporter of simulacra. The distinction between original and replication is meaningless. ",
      "TextTh": "ผมเป็นผู้สนับสนุนซิมูลาร์กเท่านั้น และคิดว่าคำว่า \"ต้นแบบ\" กับ \"ตัวลอกเลียนแบบ\"#nนั้นไม่ได้มีความหมายอะไร",
      "TextTw": "瑪艾斯托洛;雖然對支持[ruby=simulacrum]擬像論[/ruby]的我來說，區分「真品」和「複製品」沒有意義……",
      "GroupId": 204,
      "SelectionGroup": 0,
      "BGMId": 0,
      "Sound": "",
      "Transition": 0,
      "BGName": 0,
      "BGEffect": 0,
      "PopupFileName": "",
      "ScriptKr": "#na;마에스트로;뭐, 나는 시뮬라크르를 지지하는 쪽이기에, 원본이나 복제라는 구분은 무의미하다고 생각하지만……. ",
      "VoiceJp": ""
    },
    {
      "TextJp": "",
      "TextCn": "",
      "TextKr": "",
      "TextEn": "",
      "TextTh": "",
      "TextTw": "",
      "GroupId": 204,
      "SelectionGroup": 0,
      "BGMId": 0,
      "Sound": "",
      "Transition": 2482233134,
      "BGName": 4219378494,
      "BGEffect": 0,
      "PopupFileName": "",
      "ScriptKr": "3;마에스트로;00\n#3;closeup",
      "VoiceJp": ""
    },
    {
      "TextJp": "結局のところ、私たちに扱える代物ではなかった……というのが、今のところの私の結論だ。",
      "TextCn": "就结果来说，那并不是我们能够加以运用的东西……这就是我目前的结论。",
      "TextKr": "",
      "TextEn": "Ultimately, my conclusion is that the sublime of this world is beyond our control.",
      "TextTh": "แต่ท้ายที่สุดผมก็สรุปได้ว่าความสูงส่งของโลกใบนี้ คือสิ่งที่เราไม่สามารถเอื้อมถึงได้",
      "TextTw": "就結果來說，那並非我們能加以運用的東西……這是我目前的結論。",
      "GroupId": 204,
      "SelectionGroup": 0,
      "BGMId": 0,
      "Sound": "SE_Clatter_02",
      "Transition": 0,
      "BGName": 0,
      "BGEffect": 0,
      "PopupFileName": "",
      "ScriptKr": "3;마에스트로;00;결국, 이 세계의 그 숭고는 우리가 다룰 수 있는 게 아니라는 게 나의 결론이다.\n#3;closeup\n#3;stiff",
      "VoiceJp": ""
    },
    {
      "TextJp": "この結論に同意しない同志もいるだろうが、その各々の判断については私が関与すべきものではなかろう。",
      "TextCn": "也许确实有同志不同意这个结论，但他们各自的判断并不需要我来过问吧。",
      "TextKr": "",
      "TextEn": "Some of my colleagues are more than welcome to disagree. It is not my place to intervene.",
      "TextTh": "มีพวกพ้องบางคนที่ไม่เห็นด้วยกับข้อสรุปของผมอยู่ แต่ว่าพวกเขามีสิทธิ์ที่จะตัดสินใจ#nเพราะแบบนั้นผมจึงไม่มีสิทธิ์ที่จะเข้าไปแทรกแซงได้",
      "TextTw": "或許會有同志不同意我的結論，但他們各自的判斷並不需要我的參與吧。",
      "GroupId": 204,
      "SelectionGroup": 0,
      "BGMId": 0,
      "Sound": "",
      "Transition": 0,
      "BGName": 0,
      "BGEffect": 0,
      "PopupFileName": "",
      "ScriptKr": "3;마에스트로;00;나의 결론에 동의하지 않는 동지들도 있겠지만, 그 판단은 그들의 몫이니 내가 개입할 여지는 없겠지.\n#3;closeup",
      "VoiceJp": ""
    },
    {
      "TextJp": "とにかく、私たちはまた別のやり方を考えねばならなかった。",
      "TextCn": "总之，我们不得不寻找其他方法。",
      "TextKr": "",
      "TextEn": "We must approach the issue another way.",
      "TextTh": "แต่ถึงยังไง พวกเราก็ต้องคำนึงถึงวิธีอื่นด้วยเช่นกัน",
      "TextTw": "總之，我們必須想出其他作法。",
      "GroupId": 204,
      "SelectionGroup": 0,
      "BGMId": 0,
      "Sound": "",
      "Transition": 0,
      "BGName": 0,
      "BGEffect": 0,
      "PopupFileName": "",
      "ScriptKr": "3;마에스트로;00;어쨌든, 우리는 다른 방식으로 사고해야만 했다.\n#3;closeup",
      "VoiceJp": ""
    },
    {
      "TextJp": "そこで私たちは、トリニティの地下に封印されし太古の教義に目を向けた。「崇高」とは違うものの、そこに秘められた「神秘」、そして「恐怖」はまた別の意味で似ているような部分があり、つまり概念としては――",
      "TextCn": "于是我们将目光投向了圣三一地下封印着的太古教义。尽管它与“崇高”并不相同，但其隐藏的“神秘”以及“恐怖”在另一种意义上却与“崇高”有着部分相似之处，即作为一个概念──",
      "TextKr": "",
      "TextEn": "So we turned our attention to the ancient doctrines sealed below Trinity.#nThey differ from the sublime, but the Terror and Mystic they contain are somewhat similar. In theory...",
      "TextTh": "พวกเราจึงหันความสนใจไปที่ความรู้โบราณที่ถูกผนึกเอาไว้ที่ชั้นใต้ดินของทรีนิตี้#nถึงจะไม่ใช่ความสูงส่งก็ตาม แต่ความกลัวกับความลึกลับก็มีความคล้ายคลึงกันในอีกมิติหนึ่ง#nซึ่งแนวคิดนั้น...",
      "TextTw": "於是我們將目光投向了封印於三一地下的太古教義。#n儘管它與「崇高」並不相同，但其隱藏的「神秘」以及「恐怖」在別的意義上有相似之處，#n也就是說在概念上──",
      "GroupId": 204,
      "SelectionGroup": 0,
      "BGMId": 0,
      "Sound": "",
      "Transition": 0,
      "BGName": 0,
      "BGEffect": 0,
      "PopupFileName": "",
      "ScriptKr": "3;마에스트로;00;우리는 트리니티 지하에 봉인된 고대의 교의(敎義)로 관심을 돌렸다. 숭고는 아니지만, 그 공포와 신비는 다른 차원에서 비슷한 부분이 있었고…… 그 개념은…….\n#3;closeup",
      "VoiceJp": "",
      "Unsure": false
    },
    {
      "TextJp": "……失礼。",
      "TextCn": "……失礼了。",
      "TextKr": "",
      "TextEn": "...",
      "TextTh": ".....",
      "TextTw": "……失禮了。",
      "GroupId": 204,
      "SelectionGroup": 0,
      "BGMId": 0,
      "Sound": "",
      "Transition": 0,
      "BGName": 0,
      "BGEffect": 0,
      "PopupFileName": "",
      "ScriptKr": "3;마에스트로;00;…….\n#3;closeup",
      "VoiceJp": ""
    },
    {
      "TextJp": "退屈な話をしてしまったかもしれないな。すまない、先生。",
      "TextCn": "我好像说了些无聊的话呢。抱歉，老师。",
      "TextKr": "",
      "TextEn": "Am I boring you? Pardon me, Sensei.",
      "TextTh": "ช่างเป็นเรื่องน่าเบื่อจริงๆ ขอโทษทีนะ คุณครูเอ๋ย",
      "TextTw": "我好像說了些無聊的話呢。抱歉，老師。",
      "GroupId": 204,
      "SelectionGroup": 0,
      "BGMId": 0,
      "Sound": "SE_Clatter_01",
      "Transition": 0,
      "BGName": 0,
      "BGEffect": 0,
      "PopupFileName": "",
      "ScriptKr": "3;마에스트로;00;……지루한 이야기였군. 실례했다. 선생이여.\n#3;closeup\n#3;stiff",
      "VoiceJp": ""
    },
    {
      "TextJp": "つまり……私はそなたに、この小さな成功を紹介したかったのだ。",
      "TextCn": "简单来说……我想向你介绍这个微小的成功。",
      "TextKr": "",
      "TextEn": "I merely wanted to educate you on our small success.",
      "TextTh": "ผมอยากจะเล่าเรื่องความสำเร็จเล็กๆ ของเราให้ฟังสักหน่อย",
      "TextTw": "簡單來說……我想向你介紹這個小小的成功。",
      "GroupId": 204,
      "SelectionGroup": 0,
      "BGMId": 0,
      "Sound": "",
      "Transition": 0,
      "BGName": 0,
      "BGEffect": 0,
      "PopupFileName": "",
      "ScriptKr": "3;마에스트로;00;나는 우리들의 작은 성공을 소개하고 싶었던 것이다.\n#3;closeup",
      "VoiceJp": ""
    },
    {
      "TextJp": "なにせその教義はついに受肉し、その意志が天と同様に、地においても結実することが証明されようとしているのだから。",
      "TextCn": "总而言之，那个教义终于[tooltip=道成肉身，基督教基本教义之一。圣子在降世之前与圣父同体，称为“道”。后来“道”以肉身的形式降世成人，便是耶稣。所以耶稣就是道成肉身，既是完全的神，又是完全的人。]道成了肉身[/tooltip]，它试图证明其意志无论是于天上还是在地上都能结果。",
      "TextKr": "",
      "TextEn": "For the ancient doctrines will finally incarnate, proving that their will can be done below as it is in heaven.",
      "TextTh": "ความรู้โบราณนั้นจะถูกนำมาปลูกฝังและพิสูจน์ให้เห็นว่าไม่ว่าจะเป็นนรกหรือสวรรค์#nก็สามารถทำให้เจตจำนงบรรลุผลได้เช่นกัน",
      "TextTw": "那個教義總算是道成了肉身，試圖證明其意志無論於天於地都一樣結實。",
      "GroupId": 204,
      "SelectionGroup": 0,
      "BGMId": 0,
      "Sound": "",
      "Transition": 0,
      "BGName": 0,
      "BGEffect": 0,
      "PopupFileName": "",
      "ScriptKr": "3;마에스트로;00;그 고대의 교의는 마침내 수육(受肉)하여, 그 뜻이 하늘에서와 같이 지하에서도 이루어질 수 있다는 것을 증명해낼 것이니까.\n#3;closeup",
      "VoiceJp": "",
      "Unsure": false
    },
    {
      "TextJp": "",
      "TextCn": "",
      "TextKr": "",
      "TextEn": "",
      "TextTh": "",
      "TextTw": "",
      "GroupId": 204,
      "SelectionGroup": 0,
      "BGMId": 0,
      "Sound": "SE_Clatter_02",
      "Transition": 0,
      "BGName": 0,
      "BGEffect": 0,
      "PopupFileName": "",
      "ScriptKr": "3;마에스트로;00\n#3;d\n#3;closeup\n#wait;1000",
      "VoiceJp": ""
    },
    {
      "TextJp": "",
      "TextCn": "",
      "TextKr": "",
      "TextEn": "",
      "TextTh": "",
      "TextTw": "",
      "GroupId": 204,
      "SelectionGroup": 0,
      "BGMId": 0,
      "Sound": "",
      "Transition": 0,
      "BGName": 0,
      "BGEffect": 0,
      "PopupFileName": "",
      "ScriptKr": "3;마에스트로;00\n#3;a\n#wait;1500",
      "VoiceJp": ""
    },
    {
      "TextJp": "[ruby=ゲマトリア]私たち[/ruby]が作り出した、人工の天使にして、神性の怪物。",
      "TextCn": "这就是[ruby=数秘术]我们[/ruby]制造出来的人工天使、神性的怪物。",
      "TextKr": "",
      "TextEn": "An artificial angel that we created—a divine monster.",
      "TextTh": "เทวทูตประดิษฐ์ที่พวกเราสร้างขึ้นมา ปีศาจแห่งความศักดิ์สิทธิ์",
      "TextTw": "這就[ruby=蓋瑪特利亞]是我們製[/ruby]造出來的人造天使、神性的怪物。",
      "GroupId": 204,
      "SelectionGroup": 0,
      "BGMId": 0,
      "Sound": "",
      "Transition": 0,
      "BGName": 0,
      "BGEffect": 0,
      "PopupFileName": "",
      "ScriptKr": "3;마에스트로;00;우리가 만들어낸 인공천사. 신성의 괴물.",
      "VoiceJp": ""
    },
    {
      "TextJp": "紹介しよう。こちらが[ruby=Communio Sanctorum]「聖徒の交わり」[/ruby]を率いる、受肉せし教義……。",
      "TextCn": "请允许我介绍。这就是道成肉身，率领着[ruby=Communio Sanctorum]“诸圣相通”[/ruby]的教义……",
      "TextKr": "",
      "TextEn": "Allow me to introduce you. This is the doctrine that guides the Communio Sanctorum. ",
      "TextTh": "ผมขอแนะนำให้รู้จัก... นั่นก็คือคำสอนที่นำไปสู่[ruby=สหพันธ์นักบุญ]<เส้นทางร่วมกันของการเป็นผู้ใหญ่>[/ruby]",
      "TextTw": "讓我來為你介紹吧。這就是率領[ruby=Communio Sanctorum]「諸聖相通」[/ruby]的受肉教義……",
      "GroupId": 204,
      "SelectionGroup": 0,
      "BGMId": 0,
      "Sound": "SE_FootStep_03a",
      "Transition": 0,
      "BGName": 0,
      "BGEffect": 0,
      "PopupFileName": "",
      "ScriptKr": "3;마에스트로;00;소개하겠다. 이것이 바로 [ruby=Communio Sanctorum]<모든 성인의 통공通功>[/ruby]을 이끄는 교의. \n#3;m2",
      "VoiceJp": ""
    },
    {
      "TextJp": "その太古の教義に関わる名を借りて、私たちは「ヒエロニムス」と呼んでいる。",
      "TextCn": "借用与太古教义相关之名，我们将其称为[ruby=Hieronymus]“耶罗尼姆斯”[/ruby]。",
      "TextKr": "",
      "TextEn": "It is known as Hieronymus, a name borrowed from the ancient doctrines.",
      "TextTh": "และชื่อที่ได้รับมาจากความรู้โบราณนั้นก็คือ ไฮโรนีมัส",
      "TextTw": "借用與太古教義相關之名，我們將其稱為「耶羅尼姆斯」。",
      "GroupId": 204,
      "SelectionGroup": 0,
      "BGMId": 0,
      "Sound": "",
      "Transition": 0,
      "BGName": 0,
      "BGEffect": 0,
      "PopupFileName": "",
      "ScriptKr": "3;마에스트로;00;그 고대 교의의 이름을 빌려, 예로니무스라고 부르고 있다.",
      "VoiceJp": ""
    },
    {
      "TextJp": "ゆえに、こう宣言させてもらおう……もしかしたら少々前衛的だと思われるかもしれないが、私は芸術家でもあるのでそこは許してほしい。",
      "TextCn": "因此，请允许我这样宣布……或许老师会认为这份作品略显前卫，但我是个艺术家，对此还请老师见谅。",
      "TextKr": "",
      "TextEn": "Consider this the declaration of its arrival. Perhaps it's a bit avant-garde, but that suits an artist such as me, doesn't it?",
      "TextTh": "ดังนั้นผมจะขอประกาศให้รู้กันดังนี้ บางครั้งมันอาจจะรู้สึกว่าล้ำสมัยไปบ้าง#nแต่ในฐานะของศิลปินแล้ว ผมค่อนข้างชอบสิ่งเหล่านี้มากเลยล่ะ",
      "TextTw": "那麼，我這麼宣言吧……或許會被認為過於前衛，但我是個藝術家，這點還請見諒。",
      "GroupId": 204,
      "SelectionGroup": 0,
      "BGMId": 0,
      "Sound": "SE_FootStep_03b",
      "Transition": 0,
      "BGName": 0,
      "BGEffect": 0,
      "PopupFileName": "",
      "ScriptKr": "3;마에스트로;00;그러니 이렇게 선언해 보겠다. 가히 전위적이지만, 나는 예술가이기에 이런 것도 즐기는 편이지.\n#3;m3",
      "VoiceJp": ""
    },
    {
      "TextJp": "……嗚呼。かの福者はついに列聖され、聖人となり、その証として奇跡を起こさんとせん……",
      "TextCn": "……啊啊。那位承受恩典之人终于被封圣，成为了圣人。作为成圣的证明，它将引发奇迹……",
      "TextKr": "",
      "TextEn": "\"Oh, Congregatio de Causis Sanctorum, these blessed ones who gladly followed your teachings have finally been canonized, and they will perform miracles as proof.\"",
      "TextTh": "\"โอ้ เหล่านักบุญทั้งหลายเอ๋ย เหล่าผู้ที่ได้รับคำอวยพรจนได้รับ การขนานนามให้เป็นนักบุญในที่สุด#nจงแสดงปาฏิหาริย์ให้เป็นที่ประจักษ์เถิด\"",
      "TextTw": "……啊啊。那位有福之人總算受到列聖，成為了聖人。接著將引發奇蹟以玆證明……",
      "GroupId": 204,
      "SelectionGroup": 0,
      "BGMId": 0,
      "Sound": "",
      "Transition": 0,
      "BGName": 0,
      "BGEffect": 0,
      "PopupFileName": "",
      "ScriptKr": "3;마에스트로;00;\"오오, 시성성이여, 저들 복자는 예부되여 마침내 성인품에 올랐나니, 그 증거로 기적을 행하게 하리라.\"\n#3;em;…",
      "VoiceJp": ""
    },
    {
      "TextJp": "さあ、先生……どうか、どうか今一度、喝采の準備を。",
      "TextCn": "来吧，老师……务请再次，做好喝彩的准备。",
      "TextKr": "",
      "TextEn": "Here is where you give me a round of applause, Sensei.",
      "TextTh": "อ่า... ขอจงปรบมือและโห่ร้องชื่นชมให้กับผมอีกครั้งด้วยเถอะ คุณครูเอ๋ย",
      "TextTw": "來吧，老師……請再次，做好喝采的準備。",
      "GroupId": 204,
      "SelectionGroup": 0,
      "BGMId": 0,
      "Sound": "SE_Clatter_01",
      "Transition": 0,
      "BGName": 0,
      "BGEffect": 0,
      "PopupFileName": "",
      "ScriptKr": "3;마에스트로;00;아아, 그러니 이번에도 부디 갈채를 내려주기 바란다. 선생이여.\n#3;stiff",
      "VoiceJp": ""
    }
  ]
}
