{
  "GroupId": 33170,
  "translator": "たかなしち",
  "proofreader": "今天早睡了吗",
  "content": [
    {
      "TextJp": "第17話;憎しみの正体",
      "TextCn": "第17话；憎恨的真面目",
      "TextKr": "",
      "TextEn": "Episode 17;The Embodiment of Hate",
      "TextTh": "ตอนที่ 17;ตัวตนของความเกลียดชัง",
      "TextTw": "第17話;憎恨的真面目",
      "GroupId": 33170,
      "SelectionGroup": 0,
      "BGMId": 73,
      "Sound": "",
      "Transition": 0,
      "BGName": 3855938069,
      "BGEffect": 0,
      "PopupFileName": "",
      "ScriptKr": "#title;제17화;증오의 정체",
      "VoiceJp": ""
    },
    {
      "TextJp": "",
      "TextCn": "",
      "TextKr": "",
      "TextEn": "",
      "TextTh": "",
      "TextTw": "",
      "GroupId": 33170,
      "SelectionGroup": 0,
      "BGMId": 0,
      "Sound": "",
      "Transition": 0,
      "BGName": 0,
      "BGEffect": 0,
      "PopupFileName": "",
      "ScriptKr": "3;코하루;00\n#3;a\n#3;em;…\n#wait;2500",
      "VoiceJp": ""
    },
    {
      "TextJp": "どきなさい、今の状況が分からないの！？",
      "TextCn": "给我让开，你搞不清楚现在是什么状况吗！？",
      "TextKr": "",
      "TextEn": "Stand down, first-year. Can't you see what's going on?",
      "TextTh": "หลีกไปซะ เด็กปีหนึ่งไม่รู้สถานการณ์ตอนนี้รึยังไง?",
      "TextTw": "讓開，搞不清楚現在的狀況嗎！？",
      "GroupId": 33170,
      "SelectionGroup": 0,
      "BGMId": 0,
      "Sound": "",
      "Transition": 0,
      "BGName": 0,
      "BGEffect": 0,
      "PopupFileName": "",
      "ScriptKr": "1;티파티 주전파 A;05;비켜라, 1학년. 지금 무슨 상황인지도 몰라?\n#1;em;[반응]\n#1;a\n#3;m5",
      "VoiceJp": ""
    },
    {
      "TextJp": "緊急の事態なのよ！？",
      "TextCn": "现在可是紧急态势啊！？",
      "TextKr": "",
      "TextEn": "We're now under martial law and at the brink of war!",
      "TextTh": "ตอนนี้กำลังจะประกาศกฎอัยการศึกและเริ่มสงครามนะ!!",
      "TextTw": "這可是緊急事態唷！？",
      "GroupId": 33170,
      "SelectionGroup": 0,
      "BGMId": 0,
      "Sound": "",
      "Transition": 0,
      "BGName": 0,
      "BGEffect": 0,
      "PopupFileName": "",
      "ScriptKr": "1;티파티 주전파 B;07;계엄령에다가 전쟁 직전이라고!!\n#1;em;[빠직]\n#1;stiff",
      "VoiceJp": ""
    },
    {
      "TextJp": "で、でも、私は……！",
      "TextCn": "但、但是，我是……！",
      "TextKr": "",
      "TextEn": "I-I know that, but...!",
      "TextTh": "อา... คือ... ฉะ...ฉัน... คือว่า...",
      "TextTw": "可，可是，我……！",
      "GroupId": 33170,
      "SelectionGroup": 0,
      "BGMId": 0,
      "Sound": "",
      "Transition": 0,
      "BGName": 0,
      "BGEffect": 0,
      "PopupFileName": "",
      "ScriptKr": "3;코하루;04;아…… 아으…… 나, 난…… 저기…….\n#3;stiff",
      "VoiceJp": ""
    },
    {
      "TextJp": "",
      "TextCn": "",
      "TextKr": "",
      "TextEn": "",
      "TextTh": "",
      "TextTw": "",
      "GroupId": 33170,
      "SelectionGroup": 0,
      "BGMId": 0,
      "Sound": "",
      "Transition": 0,
      "BGName": 0,
      "BGEffect": 0,
      "PopupFileName": "",
      "ScriptKr": "#all;hide",
      "VoiceJp": ""
    },
    {
      "TextJp": "どけっ！！",
      "TextCn": "滚开！！",
      "TextKr": "",
      "TextEn": "Move!",
      "TextTh": "หลีกไป!!",
      "TextTw": "滾開！！",
      "GroupId": 33170,
      "SelectionGroup": 0,
      "BGMId": 0,
      "Sound": "",
      "Transition": 0,
      "BGName": 0,
      "BGEffect": 3550865647,
      "PopupFileName": "",
      "ScriptKr": "3;티파티 주전파 C;07;비켜!!\n#3;closeup\n#3;em;[!]\n#fontsize;100",
      "VoiceJp": ""
    },
    {
      "TextJp": "",
      "TextCn": "",
      "TextKr": "",
      "TextEn": "",
      "TextTh": "",
      "TextTw": "",
      "GroupId": 33170,
      "SelectionGroup": 0,
      "BGMId": 0,
      "Sound": "",
      "Transition": 0,
      "BGName": 0,
      "BGEffect": 0,
      "PopupFileName": "",
      "ScriptKr": "#all;hide",
      "VoiceJp": ""
    },
    {
      "TextJp": "",
      "TextCn": "",
      "TextKr": "",
      "TextEn": "",
      "TextTh": "",
      "TextTw": "",
      "GroupId": 33170,
      "SelectionGroup": 0,
      "BGMId": 0,
      "Sound": "",
      "Transition": 0,
      "BGName": 0,
      "BGEffect": 0,
      "PopupFileName": "",
      "ScriptKr": "#st;[0,0];instant;1;",
      "VoiceJp": ""
    },
    {
      "TextJp": "",
      "TextCn": "",
      "TextKr": "",
      "TextEn": "",
      "TextTh": "",
      "TextTw": "",
      "GroupId": 33170,
      "SelectionGroup": 0,
      "BGMId": 0,
      "Sound": "",
      "Transition": 0,
      "BGName": 0,
      "BGEffect": 0,
      "PopupFileName": "",
      "ScriptKr": "#clearST",
      "VoiceJp": ""
    },
    {
      "TextJp": "",
      "TextCn": "",
      "TextKr": "",
      "TextEn": "",
      "TextTh": "",
      "TextTw": "",
      "GroupId": 33170,
      "SelectionGroup": 0,
      "BGMId": 0,
      "Sound": "",
      "Transition": 0,
      "BGName": 0,
      "BGEffect": 0,
      "PopupFileName": "",
      "ScriptKr": "3;코하루;04\n#3;shake\n#3;em;[?!]\n#wait;1500",
      "VoiceJp": ""
    },
    {
      "TextJp": "……い、嫌っ！",
      "TextCn": "……不、不要！",
      "TextKr": "",
      "TextEn": "I won't!",
      "TextTh": "มะ...ไม่นะ!!",
      "TextTw": "……不，不要！",
      "GroupId": 33170,
      "SelectionGroup": 0,
      "BGMId": 0,
      "Sound": "",
      "Transition": 0,
      "BGName": 0,
      "BGEffect": 0,
      "PopupFileName": "",
      "ScriptKr": "3;코하루;11;……아, 안돼!\n#3;em;[반응]",
      "VoiceJp": ""
    },
    {
      "TextJp": "わ、私はバカだから、何がどうなってるのか全然分からないけど……",
      "TextCn": "因、因为我是个笨蛋，完全不知道发生了什么但是……",
      "TextKr": "",
      "TextEn": "I-I may be kinda slow, and don't fully understand what's happening...",
      "TextTh": "ฉะ...ฉันหัวไม่ค่อยดีเลยไม่รู้ว่าตอนนี้เกิดอะไรขึ้น แต่ว่า...",
      "TextTw": "我，我是笨蛋，所以完全不知道發生了什麼事……",
      "GroupId": 33170,
      "SelectionGroup": 0,
      "BGMId": 0,
      "Sound": "",
      "Transition": 0,
      "BGName": 0,
      "BGEffect": 0,
      "PopupFileName": "",
      "ScriptKr": "3;코하루;00;나, 난…… 바보라서 지금 무슨 일이 벌어지고 있는지도 잘 모르지만…… 그치만…….\n#3;stiff",
      "VoiceJp": "",
      "Unsure": false,
      "comment": ""
    },
    {
      "TextJp": "でも、これは違う！こんなの絶対にダメ！！",
      "TextCn": "但是，这是不对的！绝对不可以做这种事！！",
      "TextKr": "",
      "TextEn": "...but I know this isn't right! What you're doing is wrong!",
      "TextTh": "แบบนี้ไม่ได้นะ! เรื่องที่ไม่ได้ก็คือไม่ได้!",
      "TextTw": "但是，這是不對的！絕對不可以做這種事！！",
      "GroupId": 33170,
      "SelectionGroup": 0,
      "BGMId": 0,
      "Sound": "SE_Cartoon_01",
      "Transition": 0,
      "BGName": 0,
      "BGEffect": 0,
      "PopupFileName": "",
      "ScriptKr": "3;코하루;07;이, 이건 아니야! 아닌 건 아닌 거야!\n#3;closeup\n#3;hophop",
      "VoiceJp": ""
    },
    {
      "TextJp": "",
      "TextCn": "",
      "TextKr": "",
      "TextEn": "",
      "TextTh": "",
      "TextTw": "",
      "GroupId": 33170,
      "SelectionGroup": 0,
      "BGMId": 0,
      "Sound": "",
      "Transition": 0,
      "BGName": 0,
      "BGEffect": 0,
      "PopupFileName": "",
      "ScriptKr": "#st;[0,0];instant;1;",
      "VoiceJp": ""
    },
    {
      "TextJp": "",
      "TextCn": "",
      "TextKr": "",
      "TextEn": "",
      "TextTh": "",
      "TextTw": "",
      "GroupId": 33170,
      "SelectionGroup": 0,
      "BGMId": 0,
      "Sound": "",
      "Transition": 0,
      "BGName": 0,
      "BGEffect": 0,
      "PopupFileName": "",
      "ScriptKr": "#clearST",
      "VoiceJp": ""
    },
    {
      "TextJp": "",
      "TextCn": "",
      "TextKr": "",
      "TextEn": "",
      "TextTh": "",
      "TextTw": "",
      "GroupId": 33170,
      "SelectionGroup": 0,
      "BGMId": 999,
      "Sound": "SE_Reload_02",
      "Transition": 0,
      "BGName": 1047754314,
      "BGEffect": 0,
      "PopupFileName": "",
      "ScriptKr": "#all;hide\n#wait;500",
      "VoiceJp": ""
    },
    {
      "TextJp": "",
      "TextCn": "",
      "TextKr": "",
      "TextEn": "",
      "TextTh": "",
      "TextTw": "",
      "GroupId": 33170,
      "SelectionGroup": 0,
      "BGMId": 0,
      "Sound": "SE_Reload_03",
      "Transition": 0,
      "BGName": 0,
      "BGEffect": 0,
      "PopupFileName": "",
      "ScriptKr": "#wait;1500",
      "VoiceJp": ""
    },
    {
      "TextJp": "聞かないやつだ、それなら……",
      "TextCn": "听不懂人话的家伙，既然这样……",
      "TextKr": "",
      "TextEn": "Fine. If you won't move, then...",
      "TextTh": "ถ้าไม่หลีกไปละก็...",
      "TextTw": "不聽勸的傢伙，那樣的話……",
      "GroupId": 33170,
      "SelectionGroup": 0,
      "BGMId": 0,
      "Sound": "",
      "Transition": 0,
      "BGName": 3855938069,
      "BGEffect": 0,
      "PopupFileName": "",
      "ScriptKr": "1;티파티 주전파 B;05\n3;티파티 주전파 A;05\n5;티파티 주전파 C;05;비키지 않으면…….\n#5;em;[반응]",
      "VoiceJp": ""
    },
    {
      "TextJp": "ま、待って。この子、どこかで……。",
      "TextCn": "等、等一下。这孩子，我好像在哪里……",
      "TextKr": "",
      "TextEn": "W-Wait. I've seen this girl somewhere before.",
      "TextTh": "ดะ...เดี๋ยวก่อน ... เหมือนฉันจะเคยเห็นเด็กคนนี้จากที่ไหนมาก่อนนะ...",
      "TextTw": "等，等等。這孩子，好像在哪裡……",
      "GroupId": 33170,
      "SelectionGroup": 0,
      "BGMId": 0,
      "Sound": "",
      "Transition": 0,
      "BGName": 0,
      "BGEffect": 0,
      "PopupFileName": "",
      "ScriptKr": "3;티파티 주전파 A;01;자, 잠깐만…… 이 아이 어디선가…….\n#3;stiff",
      "VoiceJp": ""
    },
    {
      "TextJp": "よく見ると、何だか見覚えが……",
      "TextCn": "仔细看看，总觉得有些眼熟……",
      "TextKr": "",
      "TextEn": "She does look familiar...",
      "TextTh": "ทะ... ที่ไหนกันล่ะ? อะไรกัน...",
      "TextTw": "仔細看的話，感覺好像……",
      "GroupId": 33170,
      "SelectionGroup": 0,
      "BGMId": 0,
      "Sound": "",
      "Transition": 0,
      "BGName": 0,
      "BGEffect": 0,
      "PopupFileName": "",
      "ScriptKr": "1;티파티 주전파 B;04;어, 어디였지? 뭔가…….\n#1;em;…",
      "VoiceJp": ""
    },
    {
      "TextJp": "",
      "TextCn": "",
      "TextKr": "",
      "TextEn": "",
      "TextTh": "",
      "TextTw": "",
      "GroupId": 33170,
      "SelectionGroup": 0,
      "BGMId": 0,
      "Sound": "",
      "Transition": 0,
      "BGName": 0,
      "BGEffect": 0,
      "PopupFileName": "",
      "ScriptKr": "#st;[0,0];instant;1;",
      "VoiceJp": ""
    },
    {
      "TextJp": "",
      "TextCn": "",
      "TextKr": "",
      "TextEn": "",
      "TextTh": "",
      "TextTw": "",
      "GroupId": 33170,
      "SelectionGroup": 0,
      "BGMId": 0,
      "Sound": "",
      "Transition": 0,
      "BGName": 0,
      "BGEffect": 0,
      "PopupFileName": "",
      "ScriptKr": "1;티파티 주전파 B;04\n3;티파티 주전파 A;01\n5;티파티 주전파 C;05\n#1;h\n#3;h\n#5;h\n#clearST",
      "VoiceJp": ""
    },
    {
      "TextJp": "",
      "TextCn": "",
      "TextKr": "",
      "TextEn": "",
      "TextTh": "",
      "TextTw": "",
      "GroupId": 33170,
      "SelectionGroup": 0,
      "BGMId": 0,
      "Sound": "SE_FootStep_02",
      "Transition": 0,
      "BGName": 0,
      "BGEffect": 0,
      "PopupFileName": "",
      "ScriptKr": "#wait;2500",
      "VoiceJp": ""
    },
    {
      "TextJp": "[ns] \"コハルは補習授業部の、私の生徒だよ。\"",
      "TextCn": "[ns]“小春是补习部的学生。是我的学生哦。”",
      "TextKr": "",
      "TextEn": "[ns] \"Koharu belongs to the Make-Up Work Club. She's one of my students.\"",
      "TextTh": "[ns] \"โคฮารุเป็นเด็กในชมรมชั้นเรียนเสริมที่ครูดูแลอยู่นะ\"",
      "TextTw": "[ns]\"小春是補習部的，是我的學生喔。\"",
      "GroupId": 33170,
      "SelectionGroup": 0,
      "BGMId": 0,
      "Sound": "",
      "Transition": 0,
      "BGName": 0,
      "BGEffect": 0,
      "PopupFileName": "",
      "ScriptKr": "[ns] \"코하루는 내 담당의 보충수업부원이야.\"",
      "VoiceJp": ""
    },
    {
      "TextJp": "",
      "TextCn": "",
      "TextKr": "",
      "TextEn": "",
      "TextTh": "",
      "TextTw": "",
      "GroupId": 33170,
      "SelectionGroup": 0,
      "BGMId": 0,
      "Sound": "",
      "Transition": 0,
      "BGName": 0,
      "BGEffect": 0,
      "PopupFileName": "",
      "ScriptKr": "#all;hide",
      "VoiceJp": ""
    },
    {
      "TextJp": "せ、先生っ！？",
      "TextCn": "老、老师！？",
      "TextKr": "",
      "TextEn": "S-Sensei?!",
      "TextTh": "คะ... คุณครู?!",
      "TextTw": "老，老師！？",
      "GroupId": 33170,
      "SelectionGroup": 0,
      "BGMId": 12,
      "Sound": "",
      "Transition": 0,
      "BGName": 0,
      "BGEffect": 0,
      "PopupFileName": "",
      "ScriptKr": "3;코하루;04;서, 선생님?!\n#3;shake\n#3;em;[?!]",
      "VoiceJp": ""
    },
    {
      "TextJp": "……。",
      "TextCn": "……",
      "TextKr": "",
      "TextEn": "...",
      "TextTh": "...",
      "TextTw": "……",
      "GroupId": 33170,
      "SelectionGroup": 0,
      "BGMId": 0,
      "Sound": "",
      "Transition": 0,
      "BGName": 0,
      "BGEffect": 0,
      "PopupFileName": "",
      "ScriptKr": "1;미카 비무장;11;…….\n#1;stiff\n#1;a\n#3;m4",
      "VoiceJp": ""
    },
    {
      "TextJp": "",
      "TextCn": "",
      "TextKr": "",
      "TextEn": "",
      "TextTh": "",
      "TextTw": "",
      "GroupId": 33170,
      "SelectionGroup": 0,
      "BGMId": 0,
      "Sound": "",
      "Transition": 0,
      "BGName": 0,
      "BGEffect": 0,
      "PopupFileName": "",
      "ScriptKr": "#all;hide",
      "VoiceJp": ""
    },
    {
      "TextJp": "シャーレの……！？",
      "TextCn": "夏莱的……！？",
      "TextKr": "",
      "TextEn": "Th-The advisor from Schale?!",
      "TextTh": "คุณครูจากชาเล่ต์เหรอ?!",
      "TextTw": "夏萊的……！？",
      "GroupId": 33170,
      "SelectionGroup": 0,
      "BGMId": 0,
      "Sound": "",
      "Transition": 0,
      "BGName": 0,
      "BGEffect": 0,
      "PopupFileName": "",
      "ScriptKr": "5;티파티 주전파 C;04\n1;티파티 주전파 B;04\n3;티파티 주전파 A;06;샤, 샬레의 선생님?!\n#3;shake\n#3;em;[?!]",
      "VoiceJp": ""
    },
    {
      "TextJp": "そんな、意識不明の重体だったはず……？",
      "TextCn": "怎么可能，老师不应该还重伤昏迷着吗……？",
      "TextKr": "",
      "TextEn": "That can't be... We were told they were unconscious and in critical condition.",
      "TextTh": "มะ...ไม่ได้บาดเจ็บหนักจนไม่ได้สติหรอกเหรอ...?",
      "TextTw": "怎麼會，應該處於昏迷不醒的危急情況才對……？",
      "GroupId": 33170,
      "SelectionGroup": 0,
      "BGMId": 0,
      "Sound": "",
      "Transition": 0,
      "BGName": 0,
      "BGEffect": 0,
      "PopupFileName": "",
      "ScriptKr": "1;티파티 주전파 B;04;서, 설마…… 의식불명에 중상이라고 하지 않았어……?",
      "VoiceJp": ""
    },
    {
      "TextJp": "せ、先生が、どうしてここに……。",
      "TextCn": "老、老师，你为什么会来这里……",
      "TextKr": "",
      "TextEn": "What are they doing here...?",
      "TextTh": "คุณครูงั้นเหรอ...",
      "TextTw": "老，老師，為什麼會來這裡……",
      "GroupId": 33170,
      "SelectionGroup": 0,
      "BGMId": 0,
      "Sound": "",
      "Transition": 0,
      "BGName": 0,
      "BGEffect": 0,
      "PopupFileName": "",
      "ScriptKr": "5;티파티 주전파 C;04;서, 선생님이라니…….",
      "VoiceJp": ""
    },
    {
      "TextJp": "[s] \"お願いだから、まず暴力はやめてほしい。\"",
      "TextCn": "[s]“首先拜托你们能够停止现在的暴力行为。”",
      "TextKr": "",
      "TextEn": "[s] \"That's enough. Please lay down your weapons.\"",
      "TextTh": "[s] \"ครูขอร้องล่ะ เลิกใช้ความรุนแรงเถอะ\"",
      "TextTw": "[s]\"拜託妳們，先停下妳們的暴力行為。\"",
      "GroupId": 33170,
      "SelectionGroup": 0,
      "BGMId": 0,
      "Sound": "",
      "Transition": 0,
      "BGName": 0,
      "BGEffect": 0,
      "PopupFileName": "",
      "ScriptKr": "[s] \"부탁이니까, 폭력은 그만둬 줘.\"",
      "VoiceJp": ""
    },
    {
      "TextJp": "そ、それは……。",
      "TextCn": "这、这是……",
      "TextKr": "",
      "TextEn": "B-But...",
      "TextTh": "ระ... เรื่องนั้นน่ะ...",
      "TextTw": "那，那是……",
      "GroupId": 33170,
      "SelectionGroup": 0,
      "BGMId": 0,
      "Sound": "",
      "Transition": 0,
      "BGName": 0,
      "BGEffect": 0,
      "PopupFileName": "",
      "ScriptKr": "3;티파티 주전파 A;05;그, 그건…….\n#3;stiff",
      "VoiceJp": ""
    },
    {
      "TextJp": "……。",
      "TextCn": "……",
      "TextKr": "",
      "TextEn": "We've come so far...",
      "TextTh": "ตะ...ตอนนี้...",
      "TextTw": "……",
      "GroupId": 33170,
      "SelectionGroup": 0,
      "BGMId": 0,
      "Sound": "",
      "Transition": 0,
      "BGName": 0,
      "BGEffect": 0,
      "PopupFileName": "",
      "ScriptKr": "1;티파티 주전파 B;06;지, 지금은…….",
      "VoiceJp": ""
    },
    {
      "TextJp": "か、帰ろう。あの先生の表情、絶対にマズいって……。",
      "TextCn": "回、回去吧。那个老师的表情，绝对很不妙啊……",
      "TextKr": "",
      "TextEn": "I don't think Sensei is playing around...",
      "TextTh": "กลับกันเถอะ ดูสีหน้าของคุณครูสิ... แบบนี้ไม่ดีแน่",
      "TextTw": "回，回去吧。那個老師的表情，絕對很可怕啦……",
      "GroupId": 33170,
      "SelectionGroup": 0,
      "BGMId": 0,
      "Sound": "",
      "Transition": 0,
      "BGName": 0,
      "BGEffect": 0,
      "PopupFileName": "",
      "ScriptKr": "5;티파티 주전파 C;04;도, 돌아가자. 저 선생님의 표정을 봐…… 이건 좋지 않아……",
      "VoiceJp": ""
    },
    {
      "TextJp": "……ああ、行こう。",
      "TextCn": "……行，走吧。",
      "TextKr": "",
      "TextEn": "L-Let's get out of here.",
      "TextTh": "ปะ...ไปกันเถอะ",
      "TextTw": "……啊啊，走吧。",
      "GroupId": 33170,
      "SelectionGroup": 0,
      "BGMId": 0,
      "Sound": "",
      "Transition": 0,
      "BGName": 0,
      "BGEffect": 0,
      "PopupFileName": "",
      "ScriptKr": "3;티파티 주전파 A;06;가, 가자…….",
      "VoiceJp": ""
    },
    {
      "TextJp": "",
      "TextCn": "",
      "TextKr": "",
      "TextEn": "",
      "TextTh": "",
      "TextTw": "",
      "GroupId": 33170,
      "SelectionGroup": 0,
      "BGMId": 0,
      "Sound": "",
      "Transition": 0,
      "BGName": 0,
      "BGEffect": 0,
      "PopupFileName": "",
      "ScriptKr": "#st;[0,0];instant;1;",
      "VoiceJp": ""
    },
    {
      "TextJp": "",
      "TextCn": "",
      "TextKr": "",
      "TextEn": "",
      "TextTh": "",
      "TextTw": "",
      "GroupId": 33170,
      "SelectionGroup": 0,
      "BGMId": 0,
      "Sound": "SE_FootStep_01",
      "Transition": 0,
      "BGName": 0,
      "BGEffect": 0,
      "PopupFileName": "",
      "ScriptKr": "#clearST\n#wait;200",
      "VoiceJp": ""
    },
    {
      "TextJp": "",
      "TextCn": "",
      "TextKr": "",
      "TextEn": "",
      "TextTh": "",
      "TextTw": "",
      "GroupId": 33170,
      "SelectionGroup": 0,
      "BGMId": 0,
      "Sound": "SE_FootStep_02",
      "Transition": 0,
      "BGName": 0,
      "BGEffect": 0,
      "PopupFileName": "",
      "ScriptKr": "1;티파티 주전파 B;06\n5;티파티 주전파 C;04\n3;티파티 주전파 A;06\n#1;dl\n#3;dl\n#5;dl\n#wait;2500",
      "VoiceJp": ""
    },
    {
      "TextJp": "",
      "TextCn": "",
      "TextKr": "",
      "TextEn": "",
      "TextTh": "",
      "TextTw": "",
      "GroupId": 33170,
      "SelectionGroup": 0,
      "BGMId": 0,
      "Sound": "SFX_Emoticon_Motion_Twinkle",
      "Transition": 0,
      "BGName": 0,
      "BGEffect": 0,
      "PopupFileName": "",
      "ScriptKr": "3;코하루;00\n#3;a\n#wait;1500",
      "VoiceJp": ""
    },
    {
      "TextJp": "せ、先生……先生……。",
      "TextCn": "老、老师……老师……",
      "TextKr": "",
      "TextEn": "S-Sensei... Is it really you?",
      "TextTh": "คะ... คุณครู... คุณครู...",
      "TextTw": "老，老師……老師……",
      "GroupId": 33170,
      "SelectionGroup": 0,
      "BGMId": 0,
      "Sound": "",
      "Transition": 0,
      "BGName": 0,
      "BGEffect": 0,
      "PopupFileName": "",
      "ScriptKr": "3;코하루;06;서, 선생님…… 선생님…….\n#3;stiff\n#3;em;[속상함]",
      "VoiceJp": ""
    },
    {
      "TextJp": "[s] \"コハル、カッコよかったよ。流石は正義実現委員会のエリート。\"",
      "TextCn": "[s]“很帅气哦，小春。不愧是正义实现委员会的精英。”",
      "TextKr": "",
      "TextEn": "[s] \"I'm proud of how you handled that. Like a real elite.\"",
      "TextTh": "[s] \"เท่มากเลยโคฮารุ สมกับเป็นอีลีทของชมรมทวงความยุติธรรมเลยนะ\"",
      "TextTw": "[s]\"小春，很帥唷。不愧是正義實現委員會的精英。\"",
      "GroupId": 33170,
      "SelectionGroup": 0,
      "BGMId": 0,
      "Sound": "",
      "Transition": 0,
      "BGName": 0,
      "BGEffect": 0,
      "PopupFileName": "",
      "ScriptKr": "[s] \"코하루는 멋있네. 진짜 정의실현부의 엘리트야.\"",
      "VoiceJp": ""
    },
    {
      "TextJp": "先生……！",
      "TextCn": "老师……！",
      "TextKr": "",
      "TextEn": "Sensei!",
      "TextTh": "คุณครู...",
      "TextTw": "老師……！",
      "GroupId": 33170,
      "SelectionGroup": 0,
      "BGMId": 0,
      "Sound": "",
      "Transition": 0,
      "BGName": 0,
      "BGEffect": 0,
      "PopupFileName": "",
      "ScriptKr": "3;코하루;06;선생님…….",
      "VoiceJp": ""
    },
    {
      "TextJp": "",
      "TextCn": "",
      "TextKr": "",
      "TextEn": "",
      "TextTh": "",
      "TextTw": "",
      "GroupId": 33170,
      "SelectionGroup": 0,
      "BGMId": 0,
      "Sound": "",
      "Transition": 0,
      "BGName": 0,
      "BGEffect": 0,
      "PopupFileName": "",
      "ScriptKr": "#st;[0,0];instant;1;",
      "VoiceJp": ""
    },
    {
      "TextJp": "",
      "TextCn": "",
      "TextKr": "",
      "TextEn": "",
      "TextTh": "",
      "TextTw": "",
      "GroupId": 33170,
      "SelectionGroup": 0,
      "BGMId": 0,
      "Sound": "",
      "Transition": 0,
      "BGName": 0,
      "BGEffect": 0,
      "PopupFileName": "",
      "ScriptKr": "#clearST",
      "VoiceJp": ""
    },
    {
      "TextJp": "",
      "TextCn": "",
      "TextKr": "",
      "TextEn": "",
      "TextTh": "",
      "TextTw": "",
      "GroupId": 33170,
      "SelectionGroup": 0,
      "BGMId": 0,
      "Sound": "",
      "Transition": 0,
      "BGName": 0,
      "BGEffect": 0,
      "PopupFileName": "",
      "ScriptKr": "3;코하루;06\n#3;d\n#wait;1000",
      "VoiceJp": ""
    },
    {
      "TextJp": "",
      "TextCn": "",
      "TextKr": "",
      "TextEn": "",
      "TextTh": "",
      "TextTw": "",
      "GroupId": 33170,
      "SelectionGroup": 0,
      "BGMId": 0,
      "Sound": "",
      "Transition": 0,
      "BGName": 0,
      "BGEffect": 0,
      "PopupFileName": "",
      "ScriptKr": "3;미카 비무장;04\n#3;a\n#wait;1500",
      "VoiceJp": ""
    },
    {
      "TextJp": "……。",
      "TextCn": "……",
      "TextKr": "",
      "TextEn": "...",
      "TextTh": "...",
      "TextTw": "……",
      "GroupId": 33170,
      "SelectionGroup": 0,
      "BGMId": 0,
      "Sound": "",
      "Transition": 0,
      "BGName": 0,
      "BGEffect": 0,
      "PopupFileName": "",
      "ScriptKr": "3;미카 비무장;04;…….",
      "VoiceJp": ""
    },
    {
      "TextJp": "先生……。",
      "TextCn": "老师……",
      "TextKr": "",
      "TextEn": "It's really you...",
      "TextTh": "คุณ...ครู...",
      "TextTw": "老師……",
      "GroupId": 33170,
      "SelectionGroup": 0,
      "BGMId": 0,
      "Sound": "",
      "Transition": 0,
      "BGName": 0,
      "BGEffect": 0,
      "PopupFileName": "",
      "ScriptKr": "3;미카 비무장;04;선생……님…….\n#3;em;…",
      "VoiceJp": ""
    },
    {
      "TextJp": "[s] \"ミカ、大丈夫？\"",
      "TextCn": "[s]“未花，你还好吧？”",
      "TextKr": "",
      "TextEn": "[s] \"Will you be all right, Mika?\"",
      "TextTh": "[s] \"เป็นอะไรรึเปล่า มิกะ?\"",
      "TextTw": "[s]\"未花，還好嗎？\"",
      "GroupId": 33170,
      "SelectionGroup": 0,
      "BGMId": 0,
      "Sound": "",
      "Transition": 0,
      "BGName": 0,
      "BGEffect": 0,
      "PopupFileName": "",
      "ScriptKr": "[s] \"괜찮아? 미카?\"",
      "VoiceJp": ""
    },
    {
      "TextJp": "えっと……うん。",
      "TextCn": "那个……嗯。",
      "TextKr": "",
      "TextEn": "Um... Yeah.",
      "TextTh": "เอ่อ... คือ...",
      "TextTw": "那個……嗯。",
      "GroupId": 33170,
      "SelectionGroup": 0,
      "BGMId": 0,
      "Sound": "",
      "Transition": 0,
      "BGName": 0,
      "BGEffect": 0,
      "PopupFileName": "",
      "ScriptKr": "3;미카 비무장;02;……어. 저기…….",
      "VoiceJp": ""
    },
    {
      "TextJp": "何て言うか、久しぶり……だね？",
      "TextCn": "该怎么说呢，好久不见……了吧？",
      "TextKr": "",
      "TextEn": "So, uh...long time no see?",
      "TextTh": "คือว่า... ไม่เจอกันนานเลยนะ อื้อ",
      "TextTw": "該怎麼說呢，好久不見……了呢？",
      "GroupId": 33170,
      "SelectionGroup": 0,
      "BGMId": 0,
      "Sound": "",
      "Transition": 0,
      "BGName": 0,
      "BGEffect": 0,
      "PopupFileName": "",
      "ScriptKr": "3;미카 비무장;03;그, 그러니까……. 어, 오, 오랜만이지? 응.",
      "VoiceJp": ""
    },
    {
      "TextJp": "[s] \"そうだね。ミカ……ミカは、どうしてさっき……\"",
      "TextCn": "[s]“是啊。未花……未花刚才为什么……”",
      "TextKr": "",
      "TextEn": "[s] \"Yeah. Mika, why didn't you go along with them?\"",
      "TextTh": "[s] \"มิกะ เพราะอะไรกัน...?\"",
      "TextTw": "[s]\"是啊。未花……未花，為什麼妳剛才……\"",
      "GroupId": 33170,
      "SelectionGroup": 0,
      "BGMId": 0,
      "Sound": "",
      "Transition": 0,
      "BGName": 0,
      "BGEffect": 0,
      "PopupFileName": "",
      "ScriptKr": "[s] \"미카, 어째서……?\"",
      "VoiceJp": ""
    },
    {
      "TextJp": "え、あー、それは……。",
      "TextCn": "欸，啊，那个……",
      "TextKr": "",
      "TextEn": "Oh, that? Well...",
      "TextTh": "เอ๊ะ? ระ... เรื่องนั้นน่ะ...",
      "TextTw": "咦，啊，那是……",
      "GroupId": 33170,
      "SelectionGroup": 0,
      "BGMId": 0,
      "Sound": "",
      "Transition": 0,
      "BGName": 0,
      "BGEffect": 0,
      "PopupFileName": "",
      "ScriptKr": "3;미카 비무장;04;어? 뭐, 그…… 그건…….",
      "VoiceJp": ""
    },
    {
      "TextJp": "……何でだろ。絶好のチャンスだし、今立ち上がればって分かってはいるんだけど……。",
      "TextCn": "……为什么呢。虽然我知道刚才是我东山再起的绝佳机会……",
      "TextKr": "",
      "TextEn": "I wonder. I suppose it was the perfect opportunity to rid myself of Gehenna once and for all... ",
      "TextTh": "ใช่แล้ว พะ...เพราะฉันเกลียดพวกเกเฮนน่า... และตอนนี้เป็นโอกาสทอง... ",
      "TextTw": "……為什麼呢。雖然我知道這是一個東山再起的絕佳機會……",
      "GroupId": 33170,
      "SelectionGroup": 0,
      "BGMId": 0,
      "Sound": "",
      "Transition": 0,
      "BGName": 0,
      "BGEffect": 0,
      "PopupFileName": "",
      "ScriptKr": "3;미카 비무장;02;응…… 나, 나는 게헨나가 싫기 때문에…… 지금이라면 정말 절호의 기회인데……. \n#3;em;…",
      "VoiceJp": "",
      "Unsure": false
    },
    {
      "TextJp": "今でも嫌い、なんだけど……どうしてだろ……。",
      "TextCn": "我现在也还是讨厌格黑娜……为什么呢……",
      "TextKr": "",
      "TextEn": "...but I don't really have an answer. I don't know why. ",
      "TextTh": "แต่ว่า... ทำไมฉันถึงทำแบบนั้น... ",
      "TextTw": "我現在也，很討厭格黑娜的……為什麼呢……",
      "GroupId": 33170,
      "SelectionGroup": 0,
      "BGMId": 0,
      "Sound": "",
      "Transition": 0,
      "BGName": 0,
      "BGEffect": 0,
      "PopupFileName": "",
      "ScriptKr": "3;미카 비무장;01;그런데…… 나는 어째서…….",
      "VoiceJp": ""
    },
    {
      "TextJp": "私にも、よく分かんないな……。",
      "TextCn": "我也，不太明白……",
      "TextKr": "",
      "TextEn": "Even I don't really get it...",
      "TextTh": "ฉะ...ฉันก็ไม่รู้เหมือนกัน ฮ่าฮ่า... ทำไมกันนะ?",
      "TextTw": "我也，不太清楚呢……",
      "GroupId": 33170,
      "SelectionGroup": 0,
      "BGMId": 999,
      "Sound": "",
      "Transition": 0,
      "BGName": 0,
      "BGEffect": 0,
      "PopupFileName": "",
      "ScriptKr": "3;미카 비무장;16;……나, 나도 잘 모르겠어. 하하. 어째서지?\n#3;em;…",
      "VoiceJp": ""
    },
    {
      "TextJp": "あれ、ちょ、ちょっと待って……",
      "TextCn": "咦，等、等等……",
      "TextKr": "",
      "TextEn": "Wait a second...",
      "TextTh": "เอ๊ะ... เอ๋? ดะ... เดี๋ยวก่อน รอเดี๋ยวนะ",
      "TextTw": "咦，等，等一下……",
      "GroupId": 33170,
      "SelectionGroup": 0,
      "BGMId": 0,
      "Sound": "",
      "Transition": 0,
      "BGName": 0,
      "BGEffect": 0,
      "PopupFileName": "",
      "ScriptKr": "3;미카 비무장;16;어, 어라? 자, 잠깐만? 기다려 봐…….\n#3;stiff",
      "VoiceJp": ""
    },
    {
      "TextJp": "私……。",
      "TextCn": "我……",
      "TextKr": "",
      "TextEn": "Am I...?",
      "TextTh": "ฉัน...",
      "TextTw": "我……",
      "GroupId": 33170,
      "SelectionGroup": 0,
      "BGMId": 0,
      "Sound": "",
      "Transition": 0,
      "BGName": 0,
      "BGEffect": 0,
      "PopupFileName": "",
      "ScriptKr": "3;미카 비무장;17;나는…….",
      "VoiceJp": ""
    },
    {
      "TextJp": "",
      "TextCn": "",
      "TextKr": "",
      "TextEn": "",
      "TextTh": "",
      "TextTw": "",
      "GroupId": 33170,
      "SelectionGroup": 0,
      "BGMId": 0,
      "Sound": "",
      "Transition": 2482233134,
      "BGName": 3608410809,
      "BGEffect": 0,
      "PopupFileName": "",
      "ScriptKr": "#all;hide",
      "VoiceJp": ""
    },
    {
      "TextJp": "ミカ……",
      "TextCn": "未花……",
      "TextKr": "",
      "TextEn": "Mika...",
      "TextTh": "มิกะ...",
      "TextTw": "未花……",
      "GroupId": 33170,
      "SelectionGroup": 0,
      "BGMId": 35,
      "Sound": "",
      "Transition": 0,
      "BGName": 0,
      "BGEffect": 0,
      "PopupFileName": "",
      "ScriptKr": "3;세이아;04;미카…….\n#3;a",
      "VoiceJp": ""
    },
    {
      "TextJp": "その憎しみは……君が先陣に立っていた、その憎悪は……。",
      "TextCn": "那份憎恶……明明是你率先挑起的，那份憎恶……",
      "TextKr": "",
      "TextEn": "I thought your hatred would move you to capitalize on the opportunity. ",
      "TextTh": "ฉันคิดว่าถ้าเป็นคุณคงจะเปิดเผยความแค้นของตนเองได้มากกว่าคนอื่นซะอีก... ",
      "TextTw": "那股憎恨……妳率先面對的，那股憎恨……",
      "GroupId": 33170,
      "SelectionGroup": 0,
      "BGMId": 0,
      "Sound": "",
      "Transition": 0,
      "BGName": 0,
      "BGEffect": 0,
      "PopupFileName": "",
      "ScriptKr": "3;세이아;01;당신이라면 누구보다 앞장서서 자신의 그 증오를 드러낼 거라고 생각했는데…….",
      "VoiceJp": ""
    },
    {
      "TextJp": "君は、どうして……。",
      "TextCn": "你，为什么……",
      "TextKr": "",
      "TextEn": "Why would you relent now...? ",
      "TextTh": "... ทำไมคุณถึงได้.... ",
      "TextTw": "妳，為什麼……",
      "GroupId": 33170,
      "SelectionGroup": 0,
      "BGMId": 0,
      "Sound": "",
      "Transition": 0,
      "BGName": 0,
      "BGEffect": 0,
      "PopupFileName": "",
      "ScriptKr": "3;세이아;99;……. 어째서 당신은……. \n#3;em;…",
      "VoiceJp": ""
    },
    {
      "TextJp": "",
      "TextCn": "",
      "TextKr": "",
      "TextEn": "",
      "TextTh": "",
      "TextTw": "",
      "GroupId": 33170,
      "SelectionGroup": 0,
      "BGMId": 0,
      "Sound": "",
      "Transition": 2482233134,
      "BGName": 467024607,
      "BGEffect": 0,
      "PopupFileName": "",
      "ScriptKr": "#all;hide",
      "VoiceJp": ""
    },
    {
      "TextJp": "ミカさん、そろそろ聞かせていただけませんか？「アリウスと和解する」……そこにある意図を。",
      "TextCn": "未花同学，差不多该告诉我了吧？你要“与阿里乌斯和解”……的真正目的。",
      "TextKr": "",
      "TextEn": "I don't understand, Mika. What are you intentions for wanting to reconcile with Arius?",
      "TextTh": "คุณมิกะ ให้คืนดีกับทางโรงเรียนอาเรียสงั้นเหรอ มีจุดประสงค์อะไรกันแน่คะ?",
      "TextTw": "未花同學，差不多該告訴我了吧？\"和阿里烏斯和解\"……這其中的意圖。",
      "GroupId": 33170,
      "SelectionGroup": 0,
      "BGMId": 0,
      "Sound": "",
      "Transition": 0,
      "BGName": 0,
      "BGEffect": 0,
      "PopupFileName": "",
      "ScriptKr": "3;나기사;07;미카 씨. 아리우스 학원과 화해하자니, 그건 무슨 의도인 거죠?\n#3;a\n#3;em;…",
      "VoiceJp": ""
    },
    {
      "TextJp": "え、意図？",
      "TextCn": "诶？目的？",
      "TextKr": "",
      "TextEn": "Huh? My intentions...",
      "TextTh": "หืม? จุดประสงค์งั้นเหรอ...",
      "TextTw": "咦，意圖？",
      "GroupId": 33170,
      "SelectionGroup": 0,
      "BGMId": 0,
      "Sound": "",
      "Transition": 0,
      "BGName": 0,
      "BGEffect": 0,
      "PopupFileName": "",
      "ScriptKr": "3;미카;02;응? 의도라고 하면…….",
      "VoiceJp": ""
    },
    {
      "TextJp": "どういった政治的な利益があるのか……と、ナギサは聞いているんだよ。",
      "TextCn": "渚的意思是……这样做有什么政治利益。",
      "TextKr": "",
      "TextEn": "Nagisa is asking what the political benefit is to doing so.",
      "TextTh": "... นางิสะคงอยากถามว่ามีจุดประสงค์ทางการเมืองอะไรรึเปล่าน่ะค่ะ มิกะ...",
      "TextTw": "有什麼政治上的利益……渚是在這麼問唷。",
      "GroupId": 33170,
      "SelectionGroup": 0,
      "BGMId": 0,
      "Sound": "",
      "Transition": 0,
      "BGName": 0,
      "BGEffect": 0,
      "PopupFileName": "",
      "ScriptKr": "3;세이아;99;……. 나기사는 거기에 어떤 정치적 이득이 있는지를 물어보는 겁니다. 미카.",
      "VoiceJp": ""
    },
    {
      "TextJp": "別に政治的な利益っていうか……だって元々は、同じトリニティでしょ。",
      "TextCn": "也不是为了什么政治利益啦……因为我们本来就同属于圣三一嘛。",
      "TextKr": "",
      "TextEn": "That's not what I was thinking at all. They used to be one of Trinity's factions, right? Sure, it was a long time ago...",
      "TextTh": "ที่จริงแล้วที่นั่นเอง... เดิมทีก็เคยเป็นส่วนหนึ่งของสถาบันทรีนิตี้ใช่มั้ยล่ะ อื้อ ถึงจะเป็นเรื่องเล่าเก่าแก่ก็เถอะ",
      "TextTw": "要說也沒有政治上的利益吧……畢竟，我們本來就是同一個聖三一的學生吧。",
      "GroupId": 33170,
      "SelectionGroup": 0,
      "BGMId": 0,
      "Sound": "",
      "Transition": 0,
      "BGName": 0,
      "BGEffect": 0,
      "PopupFileName": "",
      "ScriptKr": "1;미카;02;그야, 거기도…… 원래는 트리니티 학원의 한 분파였잖아. 응. 예전의 이야기지만.\n#1;a\n#3;m5",
      "VoiceJp": ""
    },
    {
      "TextJp": "直接自治区に行ってさ、「仲良くしよ？」って言ってみようよ！ほら、みんなでお茶会でも開いてさ！",
      "TextCn": "我们就直接去阿里乌斯的自治区，然后和她们说“让我们做朋友吧！”对呀，然后大家就一起开个茶会嘛！",
      "TextKr": "",
      "TextEn": "...but what if we went to their district and told them we want to be friends? Then we could invite them over for tea and it would be like the good old days!",
      "TextTh": "เอาเป็นว่าฉันจะไปที่เขตปกครองตนเองอาเรียสแล้วจะขอคืนดีเอง! เหมือนที่ทางสภาน้ำชาในอดีตเคยทำ!",
      "TextTw": "直接去自治區 \"我們好好相處吧？\"這樣說看看嘛！妳看，大家一起舉辦茶會！",
      "GroupId": 33170,
      "SelectionGroup": 0,
      "BGMId": 0,
      "Sound": "",
      "Transition": 0,
      "BGName": 0,
      "BGEffect": 0,
      "PopupFileName": "",
      "ScriptKr": "1;미카;03;어떻게든 그쪽의 자치구에 찾아가서 화해를 요청해보는 거야! 과거의 티파티가 그랬던 것처럼!\n#1;em;[반짝]\n#1;hophop",
      "VoiceJp": ""
    },
    {
      "TextJp": "……。",
      "TextCn": "……",
      "TextKr": "",
      "TextEn": "...",
      "TextTh": "...",
      "TextTw": "……",
      "GroupId": 33170,
      "SelectionGroup": 0,
      "BGMId": 0,
      "Sound": "",
      "Transition": 0,
      "BGName": 0,
      "BGEffect": 0,
      "PopupFileName": "",
      "ScriptKr": "#3;hide\n5;나기사;04;…….",
      "VoiceJp": ""
    },
    {
      "TextJp": "……。",
      "TextCn": "……",
      "TextKr": "",
      "TextEn": "...",
      "TextTh": "...",
      "TextTw": "……",
      "GroupId": 33170,
      "SelectionGroup": 0,
      "BGMId": 0,
      "Sound": "",
      "Transition": 0,
      "BGName": 0,
      "BGEffect": 0,
      "PopupFileName": "",
      "ScriptKr": "5;세이아;06;…….",
      "VoiceJp": ""
    },
    {
      "TextJp": "……え、何この空気。私何か変なこと言った？",
      "TextCn": "……诶，怎么气氛成这样了。是我说了什么奇怪的话吗？",
      "TextKr": "",
      "TextEn": "What's with the awkward silence? Is there something on my face?",
      "TextTh": "เอ๊ะ บรรยากาศแบบนี้... ฉันรู้สึกเหมือนเป็นคนโง่คนเดียวเลยนะ...?",
      "TextTw": "……咦，這什麼氣氛。我說了什麼奇怪的話嗎？",
      "GroupId": 33170,
      "SelectionGroup": 0,
      "BGMId": 0,
      "Sound": "",
      "Transition": 0,
      "BGName": 0,
      "BGEffect": 0,
      "PopupFileName": "",
      "ScriptKr": "1;미카;04;어라, 이 흐름은…… 나 혼자 바보가 되는 분위기……?\n#1;em;[속상함]\n#1;stiff",
      "VoiceJp": ""
    },
    {
      "TextJp": "良いと思わない？あーあ、私がホストだったらすぐにでも動いたのに。",
      "TextCn": "不觉得很好吗？哎呀〜，换我是主持的话早就这么做了。",
      "TextKr": "",
      "TextEn": "I think it's a pretty good plan! That's what I would do if I were the host! ",
      "TextTh": "แผนนี้ไม่เลวเลยไม่ใช่รึไง? ถ้าฉันเป็นโฮสต์ละก็คงจะลงมือทำเดี๋ยวนี้เลย! ",
      "TextTw": "不覺得很好嗎？啊啊，我是主持人的話就會馬上行動的說。",
      "GroupId": 33170,
      "SelectionGroup": 0,
      "BGMId": 0,
      "Sound": "",
      "Transition": 0,
      "BGName": 0,
      "BGEffect": 0,
      "PopupFileName": "",
      "ScriptKr": "1;미카;05;나쁘지 않은 계획 아냐? 내가 호스트였다면 당장 했을 거야! \n#1;m3\n#5;dr",
      "VoiceJp": ""
    },
    {
      "TextJp": "ミカさん、あなたは本当に……まあそれは一先ず良いとして。あちらが応じるかは分からないでしょう。自治区の場所も判明していないことですし。",
      "TextCn": "未花同学，你真的是……和解暂且不提。你也不知道对方会不会答应对吧。而且她们自治区的位置我们也不清楚。\n",
      "TextKr": "",
      "TextEn": "I swear. Have you considered how they would respond at all? Not to mention that no one knows where Arius' district is in present day.",
      "TextTh": "... ก่อนอื่นก็ต้องพิจารณาว่าฝ่ายนั้นจะตอบรับด้วยรึเปล่านะคะ คุณมิกะ อีกอย่างเราไม่รู้ตำแหน่งของเขตปกครองตนเองอาเรียสด้วยค่ะ",
      "TextTw": "未花同學，妳真的是……不過這個先暫且不提。也不知道對方會不會回應吧。自治區的位置也還沒證實。",
      "GroupId": 33170,
      "SelectionGroup": 0,
      "BGMId": 0,
      "Sound": "",
      "Transition": 0,
      "BGName": 0,
      "BGEffect": 0,
      "PopupFileName": "",
      "ScriptKr": "#1;hide\n3;나기사;04;……. 일단 그쪽에서 응해줄지부터 고려해야 합니다. 미카 씨. 게다가 아리우스 자치구의 위치도 모르잖아요.",
      "VoiceJp": ""
    },
    {
      "TextJp": "それにミカ、君はもしそれが達成できたとしてどうするつもりだい？アリウスを吸収してより強大になったトリニティ……何か大きな戦いを起こそうとでも？",
      "TextCn": "再说了未花，就算你真的做到了，接下来你又打算怎么办呢？吞并了阿里乌斯，变得更加强大的圣三一……难道是想要挑起什么大规模战争吗？",
      "TextKr": "",
      "TextEn": "I'm also concerned about your intentions. Trinity would only become more powerful if Arius agreed, which could incite a war. Is that what you want?",
      "TextTh": "และอีกอย่างนะคะ มิกะ... ฉันเริ่มสงสัยเจตนาของคุณขึ้นมาแล้วค่ะ เมื่อรวมอาเรียสเข้ามา ทรีนิตี้ก็จะแข็งแกร่งขึ้น คุณคิดจะใช้ทรีนิตี้ทำอะไรงั้นเหรอคะ? หรือว่าคิดจะทำสงคราม?",
      "TextTw": "而且未花，假設成功和解了，妳打算做什麼？吸收了阿里烏斯變得更為壯大的聖三一……妳打算引起什麼大戰爭嗎？",
      "GroupId": 33170,
      "SelectionGroup": 0,
      "BGMId": 0,
      "Sound": "",
      "Transition": 0,
      "BGName": 0,
      "BGEffect": 0,
      "PopupFileName": "",
      "ScriptKr": "3;세이아;02;저는 그것보다는, 미카. 당신의 의도가 궁금하네요. 아리우스를 흡수해서 더 강력해진 트리니티로 무엇을 할 셈인 거죠? 전쟁인가요?\n#3;em;[반응]",
      "VoiceJp": ""
    },
    {
      "TextJp": "んー、まあどうするも何も無かったけど……それも良いかもね？そういう声もたくさんあるし。",
      "TextCn": "唔〜我倒也没特别想做什么啦……不过圣娅说的也不错？毕竟确实也有很多人这么想嘛。",
      "TextKr": "",
      "TextEn": "I hadn't really thought about it, but that could be fun! ",
      "TextTh": "หืม? ฮ่าฮ่าฮ่า! แบบนั้นก็ดูน่าสนุกดีนะ ",
      "TextTw": "嗯──嘛也沒有打算做什麼……不過那也不錯呢？那種意見也不少嘛。",
      "GroupId": 33170,
      "SelectionGroup": 0,
      "BGMId": 0,
      "Sound": "",
      "Transition": 0,
      "BGName": 0,
      "BGEffect": 0,
      "PopupFileName": "",
      "ScriptKr": "1;미카;10;응? 하하하, 그것도 재미있겠네. \n#1;a\n#1;em;[재잘]\n#3;m5",
      "VoiceJp": ""
    },
    {
      "TextJp": "それにそうなったら、ゲヘナをどうにかできちゃうかもしれないし？",
      "TextCn": "而且万一真的做到了，说不定还能搞定格黑娜哦？",
      "TextKr": "",
      "TextEn": "Maybe we could finally wipe out Gehenna. Isn't that what everyone wants?",
      "TextTh": "ใช้โอกาสนี้กำจัดพวกเกเฮนน่าไปเลยดีมั้ย? เห็นพวกนั้นทีไรอารมณ์เสียทุกที...",
      "TextTw": "而且變成那樣的話，還可以想辦法解決格黑娜也說不定？",
      "GroupId": 33170,
      "SelectionGroup": 0,
      "BGMId": 0,
      "Sound": "",
      "Transition": 0,
      "BGName": 0,
      "BGEffect": 0,
      "PopupFileName": "",
      "ScriptKr": "1;미카;01;그 기회에 게헨나라도 쓸어버릴까? 걔들, 기분 나쁘잖아.",
      "VoiceJp": ""
    },
    {
      "TextJp": "……。",
      "TextCn": "……",
      "TextKr": "",
      "TextEn": "...",
      "TextTh": "...",
      "TextTw": "……",
      "GroupId": 33170,
      "SelectionGroup": 0,
      "BGMId": 0,
      "Sound": "",
      "Transition": 0,
      "BGName": 0,
      "BGEffect": 0,
      "PopupFileName": "",
      "ScriptKr": "3;세이아;05;…….",
      "VoiceJp": ""
    },
    {
      "TextJp": "……なぁに、セイアちゃん。そのお顔は。",
      "TextCn": "……怎么了呀，圣娅。摆出这副表情。",
      "TextKr": "",
      "TextEn": "What's wrong Seia? Why are you looking at me like that?",
      "TextTh": "อะไรล่ะ เซอาจัง สีหน้าแบบนั้นน่ะ...",
      "TextTw": "……怎麼啦，小聖婭。擺出那副表情。",
      "GroupId": 33170,
      "SelectionGroup": 0,
      "BGMId": 0,
      "Sound": "",
      "Transition": 0,
      "BGName": 0,
      "BGEffect": 0,
      "PopupFileName": "",
      "ScriptKr": "1;미카;12;……뭐야, 세이아 쨩. 그 표정은.\n#1;em;…",
      "VoiceJp": ""
    },
    {
      "TextJp": "",
      "TextCn": "",
      "TextKr": "",
      "TextEn": "",
      "TextTh": "",
      "TextTw": "",
      "GroupId": 33170,
      "SelectionGroup": 0,
      "BGMId": 0,
      "Sound": "",
      "Transition": 2482233134,
      "BGName": 3608410809,
      "BGEffect": 0,
      "PopupFileName": "",
      "ScriptKr": "#all;hide",
      "VoiceJp": ""
    },
    {
      "TextJp": "君は自分勝手だ。あんまり何も考えていない上に衝動的で、欲張りで、時に自傷的な……",
      "TextCn": "你很任性。做事从不思考，而且冲动、贪婪，有时甚至伤害自己……",
      "TextKr": "",
      "TextEn": "You always were self-centered. You're impulsive, thoughtless, and self-destructive on top of that.",
      "TextTh": "คุณน่ะ... เป็นคนที่ทำลายตัวเองด้วยความโลภ ความใจร้อน และทำตามอำเภอใจโดยที่ไม่คิดอะไรสินะคะ",
      "TextTw": "妳很任性。沒什麼在思考又衝動、貪心，有時又會自我傷害……",
      "GroupId": 33170,
      "SelectionGroup": 0,
      "BGMId": 0,
      "Sound": "",
      "Transition": 0,
      "BGName": 0,
      "BGEffect": 0,
      "PopupFileName": "",
      "ScriptKr": "3;세이아;06;당신은…… 제멋대로에다가 별로 생각도 없고, 충동적이고, 욕심도 많은 주제에 자기 파괴적이었죠…….\n#3;a",
      "VoiceJp": ""
    },
    {
      "TextJp": "そんな君のことが、私は好きではなかったかもしれない。",
      "TextCn": "虽然我可能并不喜欢这样的你。",
      "TextKr": "",
      "TextEn": "Maybe that's why I never cared for you.",
      "TextTh": "บางทีฉันอาจจะไม่ชอบที่คุณเป็นแบบนี้ก็ได้ค่ะ",
      "TextTw": "我也許不喜歡，這樣的妳。",
      "GroupId": 33170,
      "SelectionGroup": 0,
      "BGMId": 0,
      "Sound": "",
      "Transition": 0,
      "BGName": 0,
      "BGEffect": 0,
      "PopupFileName": "",
      "ScriptKr": "3;세이아;01;저는 그런 당신이 싫었던 걸지도 몰라요.",
      "VoiceJp": ""
    },
    {
      "TextJp": "",
      "TextCn": "",
      "TextKr": "",
      "TextEn": "",
      "TextTh": "",
      "TextTw": "",
      "GroupId": 33170,
      "SelectionGroup": 0,
      "BGMId": 0,
      "Sound": "",
      "Transition": 2243764445,
      "BGName": 1047754314,
      "BGEffect": 0,
      "PopupFileName": "",
      "ScriptKr": "#all;hide",
      "VoiceJp": ""
    },
    {
      "TextJp": "",
      "TextCn": "",
      "TextKr": "",
      "TextEn": "",
      "TextTh": "",
      "TextTw": "",
      "GroupId": 33170,
      "SelectionGroup": 0,
      "BGMId": 0,
      "Sound": "",
      "Transition": 2482233134,
      "BGName": 1238116703,
      "BGEffect": 0,
      "PopupFileName": "",
      "ScriptKr": "1;아리우스 학생;01\n3;아리우스 학생;01\n5;미카;01\n#1;h\n#3;h\n#5;h",
      "VoiceJp": ""
    },
    {
      "TextJp": "……セイアちゃんはここにいる。",
      "TextCn": "……圣娅就在这里。",
      "TextKr": "",
      "TextEn": "Here. Seia's just through here. ",
      "TextTh": "ที่นี่คือที่ที่เซอาจังอยู่ ",
      "TextTw": "……小聖婭就在這裡。",
      "GroupId": 33170,
      "SelectionGroup": 0,
      "BGMId": 0,
      "Sound": "",
      "Transition": 0,
      "BGName": 0,
      "BGEffect": 0,
      "PopupFileName": "",
      "ScriptKr": "5;미카;02;……세이아 쨩이 있는 곳은 여기야. \n#5;em;[반응]",
      "VoiceJp": ""
    },
    {
      "TextJp": "静かに、病院にでも送ってくれれば……。",
      "TextCn": "只要能安静地送她进医院就行了……",
      "TextKr": "",
      "TextEn": "Now I'll be in line to become host once she takes her little extended vacation to the hospital. ",
      "TextTh": "ฉันจะส่งเซอาจังไปพักฟื้นที่โรงพยาบาลระยะยาว และจะรับตำแหน่งโฮสต์ต่อเอง อื้อ",
      "TextTw": "只要能安靜地把她送進醫院的話……",
      "GroupId": 33170,
      "SelectionGroup": 0,
      "BGMId": 0,
      "Sound": "",
      "Transition": 0,
      "BGName": 0,
      "BGEffect": 0,
      "PopupFileName": "",
      "ScriptKr": "5;미카;01;세이아 쨩은 병원에 장기요양이라도 보내놓고, 호스트 자리를 내가 가지는 거야. 응.",
      "VoiceJp": ""
    },
    {
      "TextJp": "そういうことだから、よろしくね。",
      "TextCn": "就是这样，交给你们咯。",
      "TextKr": "",
      "TextEn": "This is going to be so much fun!",
      "TextTh": "เพราะงั้น... ฝากด้วยนะ",
      "TextTw": "就是這樣，交給你們囉。",
      "GroupId": 33170,
      "SelectionGroup": 0,
      "BGMId": 0,
      "Sound": "",
      "Transition": 0,
      "BGName": 0,
      "BGEffect": 0,
      "PopupFileName": "",
      "ScriptKr": "5;미카;03;그러니까, 잘 부탁해.\n#5;em;[반짝]\n#5;greeting",
      "VoiceJp": ""
    },
    {
      "TextJp": "",
      "TextCn": "",
      "TextKr": "",
      "TextEn": "",
      "TextTh": "",
      "TextTw": "",
      "GroupId": 33170,
      "SelectionGroup": 0,
      "BGMId": 0,
      "Sound": "",
      "Transition": 0,
      "BGName": 0,
      "BGEffect": 0,
      "PopupFileName": "",
      "ScriptKr": "#st;[0,0];instant;1;",
      "VoiceJp": ""
    },
    {
      "TextJp": "",
      "TextCn": "",
      "TextKr": "",
      "TextEn": "",
      "TextTh": "",
      "TextTw": "",
      "GroupId": 33170,
      "SelectionGroup": 0,
      "BGMId": 0,
      "Sound": "",
      "Transition": 0,
      "BGName": 0,
      "BGEffect": 0,
      "PopupFileName": "",
      "ScriptKr": "#clearST",
      "VoiceJp": ""
    },
    {
      "TextJp": "",
      "TextCn": "",
      "TextKr": "",
      "TextEn": "",
      "TextTh": "",
      "TextTw": "",
      "GroupId": 33170,
      "SelectionGroup": 0,
      "BGMId": 0,
      "Sound": "",
      "Transition": 0,
      "BGName": 0,
      "BGEffect": 0,
      "PopupFileName": "",
      "ScriptKr": "3;아리우스 학생;01\n#3;em;…\n#wait;2500",
      "VoiceJp": ""
    },
    {
      "TextJp": "これについては、「スクワッド」に任せます。",
      "TextCn": "这件事情，会交给“小队”处理。",
      "TextKr": "",
      "TextEn": "Squad will handle the infiltration from here.",
      "TextTh": "ถ้าแผนการลักลอบเข้าแบบนี้ละก็ให้ทาง <สควอด> จัดการได้เลย",
      "TextTw": "關於這個，交給 \"小隊\" 處理。",
      "GroupId": 33170,
      "SelectionGroup": 0,
      "BGMId": 0,
      "Sound": "",
      "Transition": 0,
      "BGName": 0,
      "BGEffect": 0,
      "PopupFileName": "",
      "ScriptKr": "3;아리우스 학생;01;이 정도의 침투 작전은 <스쿼드>에게 맡길 겁니다.\n#3;em;[반응]",
      "VoiceJp": ""
    },
    {
      "TextJp": "……スクワッド？",
      "TextCn": "……小队？",
      "TextKr": "",
      "TextEn": "Hmm? Squad?",
      "TextTh": "หืม? สควอดเหรอ?",
      "TextTw": "……小隊？",
      "GroupId": 33170,
      "SelectionGroup": 0,
      "BGMId": 0,
      "Sound": "",
      "Transition": 0,
      "BGName": 0,
      "BGEffect": 0,
      "PopupFileName": "",
      "ScriptKr": "5;미카;02;응? 스쿼드?",
      "VoiceJp": ""
    },
    {
      "TextJp": "はい、ご存じでしょう？",
      "TextCn": "是的，您应该知道吧？",
      "TextKr": "",
      "TextEn": "Just so you know.",
      "TextTh": "รู้แค่นั้นก็พอแล้ว",
      "TextTw": "是的，您知曉吧？",
      "GroupId": 33170,
      "SelectionGroup": 0,
      "BGMId": 0,
      "Sound": "",
      "Transition": 0,
      "BGName": 0,
      "BGEffect": 0,
      "PopupFileName": "",
      "ScriptKr": "3;아리우스 학생;01;그렇게 알고 계시길.",
      "VoiceJp": ""
    },
    {
      "TextJp": "",
      "TextCn": "",
      "TextKr": "",
      "TextEn": "",
      "TextTh": "",
      "TextTw": "",
      "GroupId": 33170,
      "SelectionGroup": 0,
      "BGMId": 0,
      "Sound": "",
      "Transition": 0,
      "BGName": 0,
      "BGEffect": 0,
      "PopupFileName": "",
      "ScriptKr": "#st;[0,0];instant;1;",
      "VoiceJp": ""
    },
    {
      "TextJp": "",
      "TextCn": "",
      "TextKr": "",
      "TextEn": "",
      "TextTh": "",
      "TextTw": "",
      "GroupId": 33170,
      "SelectionGroup": 0,
      "BGMId": 0,
      "Sound": "SE_FootStep_02",
      "Transition": 0,
      "BGName": 0,
      "BGEffect": 0,
      "PopupFileName": "",
      "ScriptKr": "#clearST\n#wait;150",
      "VoiceJp": ""
    },
    {
      "TextJp": "",
      "TextCn": "",
      "TextKr": "",
      "TextEn": "",
      "TextTh": "",
      "TextTw": "",
      "GroupId": 33170,
      "SelectionGroup": 0,
      "BGMId": 0,
      "Sound": "SE_FootStep_01",
      "Transition": 0,
      "BGName": 0,
      "BGEffect": 0,
      "PopupFileName": "",
      "ScriptKr": "5;미카;09\n1;아리우스 학생;01\n3;아리우스 학생;01\n#1;dl\n#3;dl\n#5;h\n#wait;1500",
      "VoiceJp": ""
    },
    {
      "TextJp": "",
      "TextCn": "",
      "TextKr": "",
      "TextEn": "",
      "TextTh": "",
      "TextTw": "",
      "GroupId": 33170,
      "SelectionGroup": 0,
      "BGMId": 0,
      "Sound": "",
      "Transition": 2482233134,
      "BGName": 1047754314,
      "BGEffect": 0,
      "PopupFileName": "",
      "ScriptKr": "#all;hide",
      "VoiceJp": ""
    },
    {
      "TextJp": "（セイアちゃんが、死んだ……？）",
      "TextCn": "（圣娅，死了……？）",
      "TextKr": "",
      "TextEn": "(Seia's...dead?)",
      "TextTh": "(หืม...? เซอาจัง... ตาย...แล้วเหรอ?)",
      "TextTw": "（小聖婭，死了……？）",
      "GroupId": 33170,
      "SelectionGroup": 0,
      "BGMId": 0,
      "Sound": "",
      "Transition": 0,
      "BGName": 0,
      "BGEffect": 0,
      "PopupFileName": "",
      "ScriptKr": "#na;미카 비무장;(응……? 세이아 쨩이…… 죽……었다고?)",
      "VoiceJp": ""
    },
    {
      "TextJp": "（……何で？どうして？）",
      "TextCn": "（……为什么？怎么会？）",
      "TextKr": "",
      "TextEn": "(But how...? Why?) ",
      "TextTh": "(เอ๊ะ? ได้ยังไงกัน...?) ",
      "TextTw": "（……為什麼？怎麼會？）",
      "GroupId": 33170,
      "SelectionGroup": 0,
      "BGMId": 0,
      "Sound": "",
      "Transition": 0,
      "BGName": 0,
      "BGEffect": 0,
      "PopupFileName": "",
      "ScriptKr": "#na;미카 비무장;(……어라? 어째서?)",
      "VoiceJp": ""
    },
    {
      "TextJp": "（何がどうなって、え、何でそんなことに……？）",
      "TextCn": "（到底怎么了，诶，为什么变成这样……？）",
      "TextKr": "",
      "TextEn": "(How could this have happened? This isn't how things were supposed to go.)",
      "TextTh": "(อะไรกัน ทำไมถึงกลายเป็นแบบนี้...? เพราะอะไรกัน...?)",
      "TextTw": "（發生了什麼，咦，為什麼變成這樣……？）",
      "GroupId": 33170,
      "SelectionGroup": 0,
      "BGMId": 0,
      "Sound": "",
      "Transition": 0,
      "BGName": 0,
      "BGEffect": 0,
      "PopupFileName": "",
      "ScriptKr": "#na;미카 비무장;(뭐야, 어째서? 뭐가 어떻게 된 거야? 어쩌다가……?)",
      "VoiceJp": ""
    },
    {
      "TextJp": "（どうして？バカなの？だって、私は……）",
      "TextCn": "（为什么？她们是笨蛋吗？我只想，我只想……）",
      "TextKr": "",
      "TextEn": "(Is this a joke? I just wanted to...)",
      "TextTh": "(โง่หรือเปล่า... แผนที่วางเอาไว้อย่างเหมาะสม...)",
      "TextTw": "（為什麼？是笨蛋嗎？因為，我……）",
      "GroupId": 33170,
      "SelectionGroup": 0,
      "BGMId": 0,
      "Sound": "",
      "Transition": 0,
      "BGName": 0,
      "BGEffect": 0,
      "PopupFileName": "",
      "ScriptKr": "#na;미카 비무장;(바보야? 나는 그냥 적당히…….)",
      "VoiceJp": ""
    },
    {
      "TextJp": "（あれ、私……）",
      "TextCn": "（欸，我……）",
      "TextKr": "",
      "TextEn": "(Wait. Why did I do that?)",
      "TextTh": "(เกิดอะไรขึ้นน่ะ...?)",
      "TextTw": "（奇怪，我……）",
      "GroupId": 33170,
      "SelectionGroup": 0,
      "BGMId": 0,
      "Sound": "",
      "Transition": 0,
      "BGName": 0,
      "BGEffect": 0,
      "PopupFileName": "",
      "ScriptKr": "#na;미카 비무장;(……어, 어째서였지?)",
      "VoiceJp": ""
    },
    {
      "TextJp": "（私、どうしてセイアちゃんを襲撃してって指示したんだっけ……？）",
      "TextCn": "（我为什么要指示她们袭击圣娅呢……？）",
      "TextKr": "",
      "TextEn": "(Why did I order an attack on Seia?)",
      "TextTh": "(ทำไมฉันถึงสั่งให้โจมตีเซอาจัง...?)",
      "TextTw": "（我，為什麼指示襲擊小聖婭來著……？）",
      "GroupId": 33170,
      "SelectionGroup": 0,
      "BGMId": 0,
      "Sound": "",
      "Transition": 0,
      "BGName": 0,
      "BGEffect": 0,
      "PopupFileName": "",
      "ScriptKr": "#na;미카 비무장;(나, 어째서 세이아 쨩을 습격하라고 지시했더라……?)",
      "VoiceJp": ""
    },
    {
      "TextJp": "（セイアちゃんがいなくなったら、私……）",
      "TextCn": "（要是圣娅不在了，我……）",
      "TextKr": "",
      "TextEn": "(Why did I want her out of the way?)",
      "TextTh": "(ทำไมฉันถึงอยากกำจัดเซอาจังล่ะ...?)",
      "TextTw": "（小聖婭不在的話，我……）",
      "GroupId": 33170,
      "SelectionGroup": 0,
      "BGMId": 0,
      "Sound": "",
      "Transition": 0,
      "BGName": 0,
      "BGEffect": 0,
      "PopupFileName": "",
      "ScriptKr": "#na;미카 비무장;(세이아 쨩이 없어지면……. 어…… 어째서였더라……?)",
      "VoiceJp": ""
    },
    {
      "TextJp": "（……）",
      "TextCn": "（……）",
      "TextKr": "",
      "TextEn": "(...)",
      "TextTh": "(....)",
      "TextTw": "（……）",
      "GroupId": 33170,
      "SelectionGroup": 0,
      "BGMId": 0,
      "Sound": "",
      "Transition": 0,
      "BGName": 0,
      "BGEffect": 0,
      "PopupFileName": "",
      "ScriptKr": "#na;미카 비무장;(…….)",
      "VoiceJp": ""
    },
    {
      "TextJp": "（……ああ、そうだ。私は、ホストになろうとして……）",
      "TextCn": "（……啊，对了。我是，为了当上茶会主持……）",
      "TextKr": "",
      "TextEn": "(Oh, right. I wanted to be the host.) ",
      "TextTh": "(อา... ใช่แล้วล่ะ ฉัน...คิดจะรับตำแหน่งโฮสต์มานี่นา) ",
      "TextTw": "（……啊啊，對了。我，是為了當上茶會主持人……）",
      "GroupId": 33170,
      "SelectionGroup": 0,
      "BGMId": 0,
      "Sound": "",
      "Transition": 0,
      "BGName": 0,
      "BGEffect": 0,
      "PopupFileName": "",
      "ScriptKr": "#na;미카 비무장;(……아아. 그래. 맞아, 나, 호스트가 되려고 했었지.)",
      "VoiceJp": ""
    },
    {
      "TextJp": "（そう、ゲヘナのことが嫌いだったから。嫌いなものは嫌いだったから。ナギちゃんも条約とか、何か変なことをしようとしてるし）",
      "TextCn": "（没错，因为我讨厌格黑娜。因为不喜欢就是不喜欢。小渚也想搞什么条约之类的奇奇怪怪的事情）",
      "TextKr": "",
      "TextEn": "(Of course. Because I hate Gehenna so much, and Nagi is trying to force that treaty down our throats.)",
      "TextTh": "(อื้อ เพราะฉันเกลียดพวกเกเฮนน่า นางิจังเองก็พยายามทำอะไรแปลกๆ อย่างเรื่องสนธิสัญญาอยู่)",
      "TextTw": "（沒錯，因為討厭格黑娜。討厭的東西就是討厭。小渚也在搞條約什麼奇怪的事情）",
      "GroupId": 33170,
      "SelectionGroup": 0,
      "BGMId": 0,
      "Sound": "",
      "Transition": 0,
      "BGName": 0,
      "BGEffect": 0,
      "PopupFileName": "",
      "ScriptKr": "#na;미카 비무장;(응, 게헨나가 너무 싫었으니까. 나기 쨩도 조약이니 뭐니 하는 이상한 짓을 하려고 하고.)",
      "VoiceJp": ""
    },
    {
      "TextJp": "（何でそんなことするんだろ。相変わらずおバカさんなんだから。ゲヘナとの平和条約だなんて、絶対。絶対に許せない）",
      "TextCn": "（为什么要做那种事呀。小渚还是那个大笨蛋啊。要和格黑娜签和平条约，我绝对不同意。绝对）",
      "TextKr": "",
      "TextEn": "(Why would she do something like that? It's so stupid! A peace treaty with Gehenna? As if that'll ever happen. I won't let it.)",
      "TextTh": "(แล้วเรื่องอื่นทำลงไปเพราะอะไรกันแน่? บ้ารึเปล่า? สันติภาพกับเกเฮนน่าเหรอ? ฉันไม่มีทางยอมรับเด็ดขาด)",
      "TextTw": "（為什麼要做那種事呢。一如既往是個小笨蛋。和格黑娜的和平條約什麼的。我絕對，絕對不允許。）",
      "GroupId": 33170,
      "SelectionGroup": 0,
      "BGMId": 0,
      "Sound": "",
      "Transition": 0,
      "BGName": 0,
      "BGEffect": 0,
      "PopupFileName": "",
      "ScriptKr": "#na;미카 비무장;(그딴 짓을 대체 왜 하는 거야? 바보 아냐? 게헨나와 평화 조약이라고? 절대, 절대로 용납할 수 없어.)",
      "VoiceJp": ""
    },
    {
      "TextJp": "（……セイアちゃん。未来が見えるとか何とか言ってたのに、どうして自分のことも守れなかったの？それくらい見えてたんでしょ？）",
      "TextCn": "（……圣娅酱。你明明说自己能看到未来什么的，为什么连自保都做不到？这种程度的未来，你肯定能看到的吧？）",
      "TextKr": "",
      "TextEn": "(Seia said she could see the future. So why didn't she see that one coming, huh? Why didn't she protect herself?)",
      "TextTh": "(เซอาจัง หลังจากแกล้งทำเป็นมองเห็นอนาคตมาตลอด แต่สุดท้ายก็ปกป้องตัวเองไม่ได้ อื้อ ถ้าเห็นอนาคตก็ควรเตรียมการป้องกันตัวไม่ใช่รึไง?)",
      "TextTw": "（……小聖婭。明明說了看得見未來什麼的，為什麼連自己也沒辦法保護呢？那點程度的未來能看得見吧？）",
      "GroupId": 33170,
      "SelectionGroup": 0,
      "BGMId": 0,
      "Sound": "",
      "Transition": 0,
      "BGName": 0,
      "BGEffect": 0,
      "PopupFileName": "",
      "ScriptKr": "#na;미카 비무장;(세이아 쨩, 미래를 본다느니 잘난 척하더니 결국 자기 앞가림도 못하고, 응. 이 정도는 대비했어야 하는 거 아냐?)",
      "VoiceJp": ""
    },
    {
      "TextJp": "（そもそもあんなに身体も弱いのにティーパーティーに入って、いつもいつも私に「しっかり考えたまえ」って小言ばっかりで……この間だって、あんな目で私のことを……）",
      "TextCn": "（再说了，身体本来就那么弱，还要加入茶会，还总是念我说“好好想想”之类的……前段时间也是，拿那种眼神看我……）",
      "TextKr": "",
      "TextEn": "(She was too weak to be in the Tea Party to begin with. And the way she would look at me sometimes...)",
      "TextTh": "(เธออ่อนแอเกินไปที่จะเป็นสมาชิกสภาน้ำชา แถมยังมองฉันด้วยสายตาที่น่ารังเกียจ...)",
      "TextTw": "（再說了身體那麼虛弱還加入茶會，總是對我說 \"好好思考吧\" 這樣碎碎唸……之前也是，用那種眼神……）",
      "GroupId": 33170,
      "SelectionGroup": 0,
      "BGMId": 0,
      "Sound": "",
      "Transition": 0,
      "BGName": 0,
      "BGEffect": 0,
      "PopupFileName": "",
      "ScriptKr": "#na;미카 비무장;(그렇게 몸이 약한 주제에 티파티에 있었던 것부터가 잘못이고. 저번에도 더러운 걸 보는 듯한 표정으로 날 쳐다보기나 하고…….)",
      "VoiceJp": ""
    },
    {
      "TextJp": "（だから、だから……）",
      "TextCn": "（所以，所以……）",
      "TextKr": "",
      "TextEn": "(So, I mean, when you think about it...)",
      "TextTh": "(เพราะงั้นแล้ว... เพราะงั้น...)",
      "TextTw": "（所以，所以……）",
      "GroupId": 33170,
      "SelectionGroup": 0,
      "BGMId": 0,
      "Sound": "",
      "Transition": 0,
      "BGName": 0,
      "BGEffect": 0,
      "PopupFileName": "",
      "ScriptKr": "#na;미카 비무장;(그러니까…… 그러니까…….)",
      "VoiceJp": ""
    },
    {
      "TextJp": "（こうしているために、そしてゲヘナを一掃するために、これくらいの犠牲は仕方のないことだった）",
      "TextCn": "（就是这样，为了彻底消灭格黑娜，有些小牺牲也是没办法的事）",
      "TextKr": "",
      "TextEn": "(...this was inevitable. This was the sacrifice that had to happen to get rid of Gehenna.)",
      "TextTh": "(เพื่อกำจัดพวกเกเฮนน่า... การเสียสละแค่นี้เป็นเรื่องที่เลี่ยงไม่ได้นี่นะ)",
      "TextTw": "（為了這樣，還有為了一掃格黑娜，這點程度的犧牲也是沒辦法的）",
      "GroupId": 33170,
      "SelectionGroup": 0,
      "BGMId": 0,
      "Sound": "",
      "Transition": 0,
      "BGName": 0,
      "BGEffect": 0,
      "PopupFileName": "",
      "ScriptKr": "#na;미카 비무장;(……게헨나 녀석들을 치워버리기 위해선, 이 정도 희생은 어쩔 수 없는 일이었어.)",
      "VoiceJp": ""
    },
    {
      "TextJp": "（そうだった、はずなのに……）",
      "TextCn": "（明明应该是这样的……）",
      "TextKr": "",
      "TextEn": "(Yeah. That must have been it.)",
      "TextTh": "(ใช่แล้ว จริงสิ แบบนั้นแหละ)",
      "TextTw": "（明明，是那樣的……）",
      "GroupId": 33170,
      "SelectionGroup": 0,
      "BGMId": 0,
      "Sound": "",
      "Transition": 0,
      "BGName": 0,
      "BGEffect": 0,
      "PopupFileName": "",
      "ScriptKr": "#na;미카 비무장;(맞아. 그랬지. 그랬던 거야.)",
      "VoiceJp": ""
    },
    {
      "TextJp": "",
      "TextCn": "",
      "TextKr": "",
      "TextEn": "",
      "TextTh": "",
      "TextTw": "",
      "GroupId": 33170,
      "SelectionGroup": 0,
      "BGMId": 999,
      "Sound": "",
      "Transition": 2482233134,
      "BGName": 3855938069,
      "BGEffect": 0,
      "PopupFileName": "",
      "ScriptKr": "3;미카 비무장;17\n#3;h\n#3;closeup",
      "VoiceJp": ""
    },
    {
      "TextJp": "わ、私は……。",
      "TextCn": "我、我……",
      "TextKr": "",
      "TextEn": "I-I just...",
      "TextTh": "ฉะ...ฉัน... คือเรื่องนั้น...",
      "TextTw": "我，我……",
      "GroupId": 33170,
      "SelectionGroup": 0,
      "BGMId": 0,
      "Sound": "",
      "Transition": 0,
      "BGName": 0,
      "BGEffect": 0,
      "PopupFileName": "",
      "ScriptKr": "3;미카 비무장;17;나, 나는…… 그게…….\n#3;stiff\n#3;closeup",
      "VoiceJp": ""
    },
    {
      "TextJp": "……。",
      "TextCn": "……",
      "TextKr": "",
      "TextEn": "...",
      "TextTh": "...",
      "TextTw": "……",
      "GroupId": 33170,
      "SelectionGroup": 0,
      "BGMId": 0,
      "Sound": "",
      "Transition": 0,
      "BGName": 0,
      "BGEffect": 0,
      "PopupFileName": "",
      "ScriptKr": "3;미카 비무장;17;…….\n#3;em;…\n#3;closeup",
      "VoiceJp": ""
    },
    {
      "TextJp": "ごめん、セイアちゃん…………。",
      "TextCn": "对不起，圣娅酱…………",
      "TextKr": "",
      "TextEn": "I'm sorry, Seia. I didn't mean to...",
      "TextTh": "ขอโทษนะ... เซอาจัง... ฉันไม่ได้ตั้งใจจะทำแบบนั้น...",
      "TextTw": "對不起，小聖婭…………",
      "GroupId": 33170,
      "SelectionGroup": 0,
      "BGMId": 37,
      "Sound": "",
      "Transition": 0,
      "BGName": 0,
      "BGEffect": 0,
      "PopupFileName": "",
      "ScriptKr": "3;미카 비무장;18;미안해. 세이아 쨩…… 그러려고 했던 건 아니었어…….\n#3;closeup\n#3;stiff",
      "VoiceJp": ""
    },
    {
      "TextJp": "どうして、こうなったのかな……。",
      "TextCn": "为什么，会变成这样呢……",
      "TextKr": "",
      "TextEn": "I never meant for things to turn out like this.",
      "TextTh": "ฉันเองก็ไม่รู้ด้วยซ้ำว่าทำไมถึงกลายเป็นแบบนี้...",
      "TextTw": "為什麼，變成這樣了呢……",
      "GroupId": 33170,
      "SelectionGroup": 0,
      "BGMId": 0,
      "Sound": "",
      "Transition": 0,
      "BGName": 0,
      "BGEffect": 0,
      "PopupFileName": "",
      "ScriptKr": "3;미카 비무장;18;나도 이게 왜 이렇게 된 건지 모르겠어…….\n#3;closeup",
      "VoiceJp": ""
    },
    {
      "TextJp": "ごめん……ごめんね……。",
      "TextCn": "对不起……对不起啊……",
      "TextKr": "",
      "TextEn": "I'm sorry... I'm sorry!",
      "TextTh": "ขอโทษนะ... ฉันขอโทษ...",
      "TextTw": "對不起……對不起……",
      "GroupId": 33170,
      "SelectionGroup": 0,
      "BGMId": 0,
      "Sound": "",
      "Transition": 0,
      "BGName": 0,
      "BGEffect": 0,
      "PopupFileName": "",
      "ScriptKr": "3;미카 비무장;19;미안해……. 미안해…….\n#3;closeup\n#3;stiff\n#3;em;[속상함]",
      "VoiceJp": ""
    },
    {
      "TextJp": "こんなにバカで、ごめん……。",
      "TextCn": "我这么笨，对不起……",
      "TextKr": "",
      "TextEn": "I'm sorry for being such an idiot...",
      "TextTh": "ขอโทษที่ทำตัวงี่เง่าแบบนี้...",
      "TextTw": "我這麼笨，對不起……",
      "GroupId": 33170,
      "SelectionGroup": 0,
      "BGMId": 0,
      "Sound": "",
      "Transition": 0,
      "BGName": 0,
      "BGEffect": 0,
      "PopupFileName": "",
      "ScriptKr": "3;미카 비무장;19;이런 바보라서 미안해…….\n#3;closeup",
      "VoiceJp": ""
    },
    {
      "TextJp": "[s] \"ミカ……。\"",
      "TextCn": "[s]“未花……”",
      "TextKr": "",
      "TextEn": "[s] \"Mika...\"",
      "TextTh": "[s] \"มิกะ...\"",
      "TextTw": "[s]\"未花……\"",
      "GroupId": 33170,
      "SelectionGroup": 0,
      "BGMId": 0,
      "Sound": "",
      "Transition": 0,
      "BGName": 0,
      "BGEffect": 0,
      "PopupFileName": "",
      "ScriptKr": "[s] \"미카…….\"",
      "VoiceJp": ""
    },
    {
      "TextJp": "先生……私、セイアちゃんに会いたい……。",
      "TextCn": "老师……我想见见，圣娅……",
      "TextKr": "",
      "TextEn": "Sensei... I want to see Seia...",
      "TextTh": "คุณครู... ฉัน... อยากเจอเซอาจัง...",
      "TextTw": "老師……我，想見小聖婭……",
      "GroupId": 33170,
      "SelectionGroup": 0,
      "BGMId": 0,
      "Sound": "",
      "Transition": 0,
      "BGName": 0,
      "BGEffect": 0,
      "PopupFileName": "",
      "ScriptKr": "3;미카 비무장;18;선생님……, 세이아 쨩을 만나고 싶어…….\n#3;closeup",
      "VoiceJp": ""
    },
    {
      "TextJp": "ナギちゃんにも、もう一度会いたい……。",
      "TextCn": "还想，再见一次小渚……",
      "TextKr": "",
      "TextEn": "I want to see Nagi again...",
      "TextTh": "อยากเจอนางิจังอีกครั้ง...",
      "TextTw": "小渚也是，想再見一次……",
      "GroupId": 33170,
      "SelectionGroup": 0,
      "BGMId": 0,
      "Sound": "",
      "Transition": 0,
      "BGName": 0,
      "BGEffect": 0,
      "PopupFileName": "",
      "ScriptKr": "3;미카 비무장;18;나기 쨩을 다시 만나고 싶어…….\n#3;closeup",
      "VoiceJp": ""
    },
    {
      "TextJp": "こんな私じゃ、もうダメかもしれないけど……。",
      "TextCn": "虽然现在的我，可能已经没有资格了……",
      "TextKr": "",
      "TextEn": "If only I could...",
      "TextTh": "ถ้าทำได้ละก็...",
      "TextTw": "雖然這樣的我，或許已經見不到了……",
      "GroupId": 33170,
      "SelectionGroup": 0,
      "BGMId": 0,
      "Sound": "",
      "Transition": 0,
      "BGName": 0,
      "BGEffect": 0,
      "PopupFileName": "",
      "ScriptKr": "3;미카 비무장;19;그럴 수만 있다면…….\n#3;closeup",
      "VoiceJp": "",
      "Unsure": false
    },
    {
      "TextJp": "",
      "TextCn": "",
      "TextKr": "",
      "TextEn": "",
      "TextTh": "",
      "TextTw": "",
      "GroupId": 33170,
      "SelectionGroup": 0,
      "BGMId": 0,
      "Sound": "",
      "Transition": 4004024664,
      "BGName": 1047754314,
      "BGEffect": 0,
      "PopupFileName": "",
      "ScriptKr": "3;미카 비무장;19\n#3;closeup\n#3;h",
      "VoiceJp": ""
    },
    {
      "TextJp": "",
      "TextCn": "",
      "TextKr": "",
      "TextEn": "",
      "TextTh": "",
      "TextTw": "",
      "GroupId": 33170,
      "SelectionGroup": 0,
      "BGMId": 0,
      "Sound": "",
      "Transition": 0,
      "BGName": 0,
      "BGEffect": 0,
      "PopupFileName": "",
      "ScriptKr": "#wait;1000",
      "VoiceJp": ""
    },
    {
      "TextJp": "……。",
      "TextCn": "……",
      "TextKr": "",
      "TextEn": "...",
      "TextTh": "...",
      "TextTw": "……",
      "GroupId": 33170,
      "SelectionGroup": 0,
      "BGMId": 0,
      "Sound": "",
      "Transition": 0,
      "BGName": 0,
      "BGEffect": 0,
      "PopupFileName": "",
      "ScriptKr": "#na;세이아;…….",
      "VoiceJp": ""
    },
    {
      "TextJp": "ミカ、君は……。",
      "TextCn": "未花，你……",
      "TextKr": "",
      "TextEn": "Now I understand, Mika.",
      "TextTh": "ใช่แล้วค่ะ มิกะ... คุณน่ะ... ที่จริงแล้ว... ก็แค่...",
      "TextTw": "未花，妳……",
      "GroupId": 33170,
      "SelectionGroup": 0,
      "BGMId": 0,
      "Sound": "",
      "Transition": 0,
      "BGName": 0,
      "BGEffect": 0,
      "PopupFileName": "",
      "ScriptKr": "#na;세이아;그랬나요. 미카. 당신은…… 사실은……. 그저…….",
      "VoiceJp": ""
    },
    {
      "TextJp": "そうか、理由を求めていたのか……。",
      "TextCn": "原来如此，原来是在寻求一个理由啊……",
      "TextKr": "",
      "TextEn": "You were only trying to rationalize what happened.",
      "TextTh": "แค่ต้องการเหตุผลที่เหมาะสมก็เท่านั้น",
      "TextTw": "是嗎，在尋求理由嗎……",
      "GroupId": 33170,
      "SelectionGroup": 0,
      "BGMId": 0,
      "Sound": "",
      "Transition": 0,
      "BGName": 0,
      "BGEffect": 0,
      "PopupFileName": "",
      "ScriptKr": "#na;세이아;그저, 적당한 이유가 필요했던 건가요…….",
      "VoiceJp": ""
    },
    {
      "TextJp": "嫌いであることに何かしっかりしたものが必要なのではと、どこかで合理化しようと……。",
      "TextCn": "想要为自己的厌恶寻找一个确切的理由，想要找办法将它合理化……",
      "TextKr": "",
      "TextEn": "You were trying to protect your heart and conscience.",
      "TextTh": "คุณแค่หาเหตุผลเพื่อเข้าข้างตัวเองว่าเรื่องผิวเผินพวกนั้นเป็นเรื่องของคุณ...",
      "TextTw": "對於討厭的事物需要某個確切的原因，試圖在某處合理化……",
      "GroupId": 33170,
      "SelectionGroup": 0,
      "BGMId": 0,
      "Sound": "",
      "Transition": 0,
      "BGName": 0,
      "BGEffect": 0,
      "PopupFileName": "",
      "ScriptKr": "#na;세이아;당신은 그런 피상적인 것을 자신의 것이라고 스스로를 합리화했던 거군요.",
      "VoiceJp": ""
    },
    {
      "TextJp": "そうして間違いが合わさって……相変わらず、馬鹿なことを……。",
      "TextCn": "然后将错就错……你还是老样子，尽做些傻事……",
      "TextKr": "",
      "TextEn": "And, as usual, you made mistakes and got carried away.",
      "TextTh": "ทำไมถึงได้ทำเรื่องที่โง่เขลาและน่าเวทนาแบบนี้กันนะ... มิกะ...",
      "TextTw": "妳將錯就錯……還是一樣，是個笨蛋……",
      "GroupId": 33170,
      "SelectionGroup": 0,
      "BGMId": 0,
      "Sound": "",
      "Transition": 0,
      "BGName": 0,
      "BGEffect": 0,
      "PopupFileName": "",
      "ScriptKr": "#na;세이아;이 어찌나 한심하고 바보같은 행동인가요……. 미카…….",
      "VoiceJp": ""
    },
    {
      "TextJp": "",
      "TextCn": "",
      "TextKr": "",
      "TextEn": "",
      "TextTh": "",
      "TextTw": "",
      "GroupId": 33170,
      "SelectionGroup": 0,
      "BGMId": 0,
      "Sound": "",
      "Transition": 2482233134,
      "BGName": 3608410809,
      "BGEffect": 0,
      "PopupFileName": "",
      "ScriptKr": "3;세이아;01\n#3;closeup\n#3;h",
      "VoiceJp": ""
    },
    {
      "TextJp": "……。",
      "TextCn": "……",
      "TextKr": "",
      "TextEn": "...",
      "TextTh": "...",
      "TextTw": "……",
      "GroupId": 33170,
      "SelectionGroup": 0,
      "BGMId": 0,
      "Sound": "",
      "Transition": 0,
      "BGName": 0,
      "BGEffect": 0,
      "PopupFileName": "",
      "ScriptKr": "3;세이아;01;…….\n#3;closeup",
      "VoiceJp": ""
    },
    {
      "TextJp": "私は君のことを、分かったつもりでいた。きっとまだこれだけじゃない……君の抱えていたものを、幼気な感情を、考えていたことを、その状況を……それらを知ろうとする努力を、私は怠っていた。",
      "TextCn": "我本以为我足够了解你。但我对你的了解一定远远不够……你背负的东西，你稚嫩的感情，你思考的事情，你所处的状况……我为了解它们做出的努力还远远不够。",
      "TextKr": "",
      "TextEn": "I thought I had you all figured out. I thought I understood what kind of person you were and what kind of thoughts you have...",
      "TextTh": "แทนที่จะพยายามเข้าใจว่าคุณคิดยังไง หรือเป็นคนยังไง ฉันคิดว่าตัวเองรู้จักคุณแล้ว",
      "TextTw": "我自以為理解了妳。但我要理解的妳肯定不只如此……妳所擁有的事物，妳幼稚的感情，妳所思考的事情，對於這些狀況……我應該要知曉這些的努力，全都被我怠慢了。",
      "GroupId": 33170,
      "SelectionGroup": 0,
      "BGMId": 0,
      "Sound": "",
      "Transition": 0,
      "BGName": 0,
      "BGEffect": 0,
      "PopupFileName": "",
      "ScriptKr": "3;세이아;08;저는 당신이 어떤 사람인지, 어떤 생각을 하는지 알려고 노력하는 대신…… 이미 당신이란 사람을 알고 있다고 생각했습니다.\n#3;closeup",
      "VoiceJp": "",
      "Unsure": false
    },
    {
      "TextJp": "……そうか。",
      "TextCn": "……是这样啊。",
      "TextKr": "",
      "TextEn": "...but I was mistaken. ",
      "TextTh": "ใช่แล้วค่ะ ",
      "TextTw": "……是這樣啊。",
      "GroupId": 33170,
      "SelectionGroup": 0,
      "BGMId": 0,
      "Sound": "",
      "Transition": 0,
      "BGName": 0,
      "BGEffect": 0,
      "PopupFileName": "",
      "ScriptKr": "3;세이아;01;……그러네요. \n#3;closeup",
      "VoiceJp": ""
    },
    {
      "TextJp": "私はまだ、君のことをあまりにも知らない……。",
      "TextCn": "我对你，还是一无所知啊……",
      "TextKr": "",
      "TextEn": "We both still have a lot to learn, then.",
      "TextTh": "แต่ที่จริงแล้วฉันไม่รู้เรื่องอะไรเกี่ยวกับคุณเลย",
      "TextTw": "我還，對妳一無所知……",
      "GroupId": 33170,
      "SelectionGroup": 0,
      "BGMId": 0,
      "Sound": "",
      "Transition": 0,
      "BGName": 0,
      "BGEffect": 0,
      "PopupFileName": "",
      "ScriptKr": "3;세이아;99;저 역시 당신에 대해서 아무것도 모르고 있었던 것이었군요.\n#3;closeup",
      "VoiceJp": ""
    },
    {
      "TextJp": "……そして、気が付いた時には君も私と同じように。間違った物語の真ん中に置かれていたのか。",
      "TextCn": "……然后，当你回过神来时，发现自己也被置身于一个错误的故事中心。就像我一样。",
      "TextKr": "",
      "TextEn": "You found yourself at the wrong end of a twisted fairy tale before you could even realize it, just like me.",
      "TextTh": "พอทบทวนดูแล้ว คุณเองก็เหมือนกับฉันที่อยู่ท่ามกลางเรื่องราวที่ผิดเพี้ยนไป...",
      "TextTw": "……於是，回過神來時妳已經和我一樣。被置身於錯誤的故事之中了嗎。",
      "GroupId": 33170,
      "SelectionGroup": 0,
      "BGMId": 0,
      "Sound": "",
      "Transition": 0,
      "BGName": 0,
      "BGEffect": 0,
      "PopupFileName": "",
      "ScriptKr": "3;세이아;06;……정신을 차려보니 당신도 저처럼 잘못된 이야기의 한 가운데에 놓여 있었던 거군요.\n#3;closeup\n#3;em;…",
      "VoiceJp": ""
    },
    {
      "TextJp": "殺人、死、裏切り、抗争……。",
      "TextCn": "杀戮、死亡、背叛、纷争……",
      "TextKr": "",
      "TextEn": "Murder, death, betrayal, strife...",
      "TextTh": "การเข่นฆ่า... ความตาย... การทรยศ... สงคราม...",
      "TextTw": "殺人、死亡、背叛、抗爭……",
      "GroupId": 33170,
      "SelectionGroup": 0,
      "BGMId": 0,
      "Sound": "",
      "Transition": 0,
      "BGName": 0,
      "BGEffect": 0,
      "PopupFileName": "",
      "ScriptKr": "3;세이아;06;살인…… 죽음…… 배신…… 전쟁…….\n#3;closeup",
      "VoiceJp": ""
    },
    {
      "TextJp": "君のような少女が身を置くには、あまりにも残酷な話だった。本来であれば許されるべき我儘が、君を……",
      "TextCn": "让你这样的少女置身其中，实在是太过残酷。\n你那本应得到宽恕的任性，却让你……",
      "TextKr": "",
      "TextEn": "It was too grim of a story for a girl like you to be involved with.",
      "TextTh": "การที่เด็กสาวอย่างคุณเข้ามาเกี่ยวข้องกับเรื่องพวกนี้ มันน่าเศร้ามากเลยนะคะ",
      "TextTw": "讓妳這樣的少女置身其中，未免也太殘酷了。本來應該獲得原諒的任性，讓妳……",
      "GroupId": 33170,
      "SelectionGroup": 0,
      "BGMId": 0,
      "Sound": "",
      "Transition": 0,
      "BGName": 0,
      "BGEffect": 0,
      "PopupFileName": "",
      "ScriptKr": "3;세이아;01;당신 같은 소녀가 몸담기엔 너무나 이상한 이야기였던 것이었네요.\n#3;closeup",
      "VoiceJp": ""
    },
    {
      "TextJp": "……ミカ。",
      "TextCn": "……未花。",
      "TextKr": "",
      "TextEn": "Mika...",
      "TextTh": "มิกะ...",
      "TextTw": "……未花。",
      "GroupId": 33170,
      "SelectionGroup": 0,
      "BGMId": 0,
      "Sound": "",
      "Transition": 0,
      "BGName": 0,
      "BGEffect": 0,
      "PopupFileName": "",
      "ScriptKr": "3;세이아;01;미카…….\n#3;closeup",
      "VoiceJp": ""
    },
    {
      "TextJp": "君も、ずっと……。",
      "TextCn": "你也，一直……",
      "TextKr": "",
      "TextEn": "You've been suffering for quite some time...",
      "TextTh": "คุณเองก็ทุกข์ทรมานมาโดยตลอดสินะคะ",
      "TextTw": "妳也，一直……",
      "GroupId": 33170,
      "SelectionGroup": 0,
      "BGMId": 0,
      "Sound": "",
      "Transition": 0,
      "BGName": 0,
      "BGEffect": 0,
      "PopupFileName": "",
      "ScriptKr": "3;세이아;00;당신도 줄곧 고통받고 있었군요.\n#3;closeup",
      "VoiceJp": ""
    },
    {
      "TextJp": "……とにかく私は、君を許そう。",
      "TextCn": "……总之，我会原谅你。",
      "TextKr": "",
      "TextEn": "...so I'll forgive you.",
      "TextTh": "ฉันยกโทษให้คุณค่ะ",
      "TextTw": "……總之我，原諒妳吧。",
      "GroupId": 33170,
      "SelectionGroup": 0,
      "BGMId": 0,
      "Sound": "",
      "Transition": 0,
      "BGName": 0,
      "BGEffect": 0,
      "PopupFileName": "",
      "ScriptKr": "3;세이아;01;……당신을 용서하겠습니다.\n#3;closeup",
      "VoiceJp": ""
    },
    {
      "TextJp": "そして私もまた、君に許しを乞わなくてはならないのかもしれない。",
      "TextCn": "然后，我也许也不得不向你祈求宽恕。",
      "TextKr": "",
      "TextEn": "Maybe I should be asking for your forgiveness as well.",
      "TextTh": "ไม่สิ... บางทีฉันอาจเป็นคนที่จะต้องขอให้คุณยกโทษให้ด้วยซ้ำ",
      "TextTw": "接著，我也必須向妳尋求妳的原諒也說不定。",
      "GroupId": 33170,
      "SelectionGroup": 0,
      "BGMId": 0,
      "Sound": "",
      "Transition": 0,
      "BGName": 0,
      "BGEffect": 0,
      "PopupFileName": "",
      "ScriptKr": "3;세이아;06;아니, 어쩌면 저 또한 용서를 구해야 할지도 몰라요.\n#3;closeup",
      "VoiceJp": ""
    },
    {
      "TextJp": "私たちはもう一度お互いに伝えあって、それで……もしかしたらその先は……",
      "TextCn": "我们会再一次相互交心，然后……也许在那之后……",
      "TextKr": "",
      "TextEn": "We'll have a lot of catching up to do in the future.",
      "TextTh": "พวกเรา... ต้องได้มาพบกันและบอกเล่าเรื่องราวทั้งหมดอีกครั้งค่ะ...",
      "TextTw": "我們再一次相互傳達彼此的想法給對方，然後……搞不好那之後……",
      "GroupId": 33170,
      "SelectionGroup": 0,
      "BGMId": 0,
      "Sound": "",
      "Transition": 0,
      "BGName": 0,
      "BGEffect": 0,
      "PopupFileName": "",
      "ScriptKr": "3;세이아;01;우리들은…… 만나서 다시 한번 그 모든 것들을 서로에게 전하지 않으면 안 되겠네요…….\n#3;closeup",
      "VoiceJp": ""
    },
    {
      "TextJp": "",
      "TextCn": "",
      "TextKr": "",
      "TextEn": "",
      "TextTh": "",
      "TextTw": "",
      "GroupId": 33170,
      "SelectionGroup": 0,
      "BGMId": 0,
      "Sound": "",
      "Transition": 2482233134,
      "BGName": 3855938069,
      "BGEffect": 0,
      "PopupFileName": "",
      "ScriptKr": "3;미카 비무장;19\n#3;h\n#3;closeup",
      "VoiceJp": ""
    },
    {
      "TextJp": "[ns] \"……任せて、ミカ。\"",
      "TextCn": "[ns]“……交给我吧，未花。”",
      "TextKr": "",
      "TextEn": "[ns] \"Sure. I can make that happen.\"",
      "TextTh": "[ns] \"ได้อยู่แล้ว ไว้ใจครูนะ มิกะ\"",
      "TextTw": "[ns]\"……交給我吧，未花。\"",
      "GroupId": 33170,
      "SelectionGroup": 0,
      "BGMId": 0,
      "Sound": "",
      "Transition": 0,
      "BGName": 0,
      "BGEffect": 0,
      "PopupFileName": "",
      "ScriptKr": "[ns] \"물론이야. 맡겨줘. 미카.\"",
      "VoiceJp": ""
    },
    {
      "TextJp": "",
      "TextCn": "",
      "TextKr": "",
      "TextEn": "",
      "TextTh": "",
      "TextTw": "",
      "GroupId": 33170,
      "SelectionGroup": 0,
      "BGMId": 0,
      "Sound": "",
      "Transition": 0,
      "BGName": 0,
      "BGEffect": 0,
      "PopupFileName": "",
      "ScriptKr": "5;코하루;05\n3;미카 비무장;19\n#3;m2\n#5;a\n#3;h\n#5;h\n#wait;2500",
      "VoiceJp": ""
    },
    {
      "TextJp": "",
      "TextCn": "",
      "TextKr": "",
      "TextEn": "",
      "TextTh": "",
      "TextTw": "",
      "GroupId": 33170,
      "SelectionGroup": 0,
      "BGMId": 0,
      "Sound": "",
      "Transition": 1272583944,
      "BGName": 1047754314,
      "BGEffect": 0,
      "PopupFileName": "",
      "ScriptKr": "#all;hide",
      "VoiceJp": ""
    },
    {
      "TextJp": "",
      "TextCn": "",
      "TextKr": "",
      "TextEn": "",
      "TextTh": "",
      "TextTw": "",
      "GroupId": 33170,
      "SelectionGroup": 0,
      "BGMId": 999,
      "Sound": "",
      "Transition": 0,
      "BGName": 0,
      "BGEffect": 0,
      "PopupFileName": "",
      "ScriptKr": "#wait;1500",
      "VoiceJp": ""
    },
    {
      "TextJp": "",
      "TextCn": "",
      "TextKr": "",
      "TextEn": "",
      "TextTh": "",
      "TextTw": "",
      "GroupId": 33170,
      "SelectionGroup": 0,
      "BGMId": 0,
      "Sound": "",
      "Transition": 2457385855,
      "BGName": 3031703630,
      "BGEffect": 0,
      "PopupFileName": "",
      "ScriptKr": "#all;hide",
      "VoiceJp": ""
    },
    {
      "TextJp": "",
      "TextCn": "",
      "TextKr": "",
      "TextEn": "",
      "TextTh": "",
      "TextTw": "",
      "GroupId": 33170,
      "SelectionGroup": 0,
      "BGMId": 0,
      "Sound": "SE_Crowd_02",
      "Transition": 0,
      "BGName": 0,
      "BGEffect": 0,
      "PopupFileName": "",
      "ScriptKr": "#wait;1500",
      "VoiceJp": ""
    },
    {
      "TextJp": "せ、先生だ……。",
      "TextCn": "是、是老师……",
      "TextKr": "",
      "TextEn": "I-It's Sensei...",
      "TextTh": "คะ...คุณครูล่ะ...",
      "TextTw": "是，是老師……",
      "GroupId": 33170,
      "SelectionGroup": 0,
      "BGMId": 32,
      "Sound": "",
      "Transition": 0,
      "BGName": 0,
      "BGEffect": 0,
      "PopupFileName": "",
      "ScriptKr": "3;티파티 행정관;02;서, 선생님이다…….\n#3;a\n#3;em;…\n#3;stiff",
      "VoiceJp": ""
    },
    {
      "TextJp": "先生……。",
      "TextCn": "老师……",
      "TextKr": "",
      "TextEn": "Impossible...",
      "TextTh": "คุณครู...",
      "TextTw": "老師……",
      "GroupId": 33170,
      "SelectionGroup": 0,
      "BGMId": 0,
      "Sound": "",
      "Transition": 0,
      "BGName": 0,
      "BGEffect": 0,
      "PopupFileName": "",
      "ScriptKr": "1;시스터후드 행정관;02;선생님…….\n#1;a",
      "VoiceJp": ""
    },
    {
      "TextJp": "先生……！？",
      "TextCn": "老师……！ ？",
      "TextKr": "",
      "TextEn": "Sensei is back...?",
      "TextTh": "คุณครู...",
      "TextTw": "老師……！？",
      "GroupId": 33170,
      "SelectionGroup": 0,
      "BGMId": 0,
      "Sound": "",
      "Transition": 0,
      "BGName": 0,
      "BGEffect": 0,
      "PopupFileName": "",
      "ScriptKr": "5;정의실현부 부원;03;선생님…….\n#5;a",
      "VoiceJp": ""
    },
    {
      "TextJp": "[s] \"みんな、待たせてごめん。\"",
      "TextCn": "[s]“抱歉，让大家久等了。”",
      "TextKr": "",
      "TextEn": "[s] \"Thank you all for coming.\"",
      "TextTh": "[s] \"ขอบคุณทุกคนที่มานะ\"",
      "TextTw": "[s]\"大家，抱歉久等了。\"",
      "GroupId": 33170,
      "SelectionGroup": 0,
      "BGMId": 0,
      "Sound": "",
      "Transition": 0,
      "BGName": 0,
      "BGEffect": 0,
      "PopupFileName": "",
      "ScriptKr": "[s] \"모두 모여줘서 고마워.\"",
      "VoiceJp": ""
    },
    {
      "TextJp": "",
      "TextCn": "",
      "TextKr": "",
      "TextEn": "",
      "TextTh": "",
      "TextTw": "",
      "GroupId": 33170,
      "SelectionGroup": 0,
      "BGMId": 0,
      "Sound": "",
      "Transition": 0,
      "BGName": 0,
      "BGEffect": 0,
      "PopupFileName": "",
      "ScriptKr": "#st;[0,0];instant;1;",
      "VoiceJp": ""
    },
    {
      "TextJp": "",
      "TextCn": "",
      "TextKr": "",
      "TextEn": "",
      "TextTh": "",
      "TextTw": "",
      "GroupId": 33170,
      "SelectionGroup": 0,
      "BGMId": 0,
      "Sound": "",
      "Transition": 0,
      "BGName": 0,
      "BGEffect": 0,
      "PopupFileName": "",
      "ScriptKr": "#clearST",
      "VoiceJp": ""
    },
    {
      "TextJp": "",
      "TextCn": "",
      "TextKr": "",
      "TextEn": "",
      "TextTh": "",
      "TextTw": "",
      "GroupId": 33170,
      "SelectionGroup": 0,
      "BGMId": 0,
      "Sound": "",
      "Transition": 0,
      "BGName": 0,
      "BGEffect": 0,
      "PopupFileName": "",
      "ScriptKr": "3;티파티 행정관;02\n1;시스터후드 행정관;02\n5;정의실현부 부원;03\n#1;d\n#3;d\n#5;d\n#wait;1000",
      "VoiceJp": ""
    },
    {
      "TextJp": "先生……。",
      "TextCn": "老师……",
      "TextKr": "",
      "TextEn": "Sensei...",
      "TextTh": "คุณครู...",
      "TextTw": "老師……",
      "GroupId": 33170,
      "SelectionGroup": 0,
      "BGMId": 0,
      "Sound": "",
      "Transition": 0,
      "BGName": 0,
      "BGEffect": 0,
      "PopupFileName": "",
      "ScriptKr": "3;하나코;01;선생님…….\n#3;a",
      "VoiceJp": ""
    },
    {
      "TextJp": "先生……！",
      "TextCn": "老师……！",
      "TextKr": "",
      "TextEn": "Welcome back.",
      "TextTh": "คุณครู...",
      "TextTw": "老師……！",
      "GroupId": 33170,
      "SelectionGroup": 0,
      "BGMId": 0,
      "Sound": "",
      "Transition": 0,
      "BGName": 0,
      "BGEffect": 0,
      "PopupFileName": "",
      "ScriptKr": "1;마리;01;선생님…….\n#1;a",
      "VoiceJp": ""
    },
    {
      "TextJp": "……っ。",
      "TextCn": "……",
      "TextKr": "",
      "TextEn": "Y-Yeah!",
      "TextTh": "อะ...อื้อ...!",
      "TextTw": "……",
      "GroupId": 33170,
      "SelectionGroup": 0,
      "BGMId": 0,
      "Sound": "",
      "Transition": 0,
      "BGName": 0,
      "BGEffect": 0,
      "PopupFileName": "",
      "ScriptKr": "5;코하루;00;으, 응……!\n#5;a\n#5;em;[!]\n#5;stiff",
      "VoiceJp": ""
    },
    {
      "TextJp": "",
      "TextCn": "",
      "TextKr": "",
      "TextEn": "",
      "TextTh": "",
      "TextTw": "",
      "GroupId": 33170,
      "SelectionGroup": 0,
      "BGMId": 0,
      "Sound": "",
      "Transition": 0,
      "BGName": 0,
      "BGEffect": 0,
      "PopupFileName": "",
      "ScriptKr": "3;하나코;01\n1;마리;01\n5;코하루;00\n#1;h\n#3;h\n#5;h",
      "VoiceJp": ""
    },
    {
      "TextJp": "[ns] \"ここにいてくれて、待っててくれてありがとう。\"",
      "TextCn": "[ns]“谢谢你们在这里等着我。”",
      "TextKr": "",
      "TextEn": "[ns] \"Thanks for waiting.\"",
      "TextTh": "[ns] \"ขอบคุณทุกคนที่รอครูนะ\"",
      "TextTw": "[ns]\"謝謝妳們待在這裡，等我回來。\"",
      "GroupId": 33170,
      "SelectionGroup": 0,
      "BGMId": 0,
      "Sound": "",
      "Transition": 0,
      "BGName": 0,
      "BGEffect": 0,
      "PopupFileName": "",
      "ScriptKr": "[ns] \"모두들 기다려줘서 고마워.\"",
      "VoiceJp": ""
    },
    {
      "TextJp": "",
      "TextCn": "",
      "TextKr": "",
      "TextEn": "",
      "TextTh": "",
      "TextTw": "",
      "GroupId": 33170,
      "SelectionGroup": 0,
      "BGMId": 0,
      "Sound": "",
      "Transition": 0,
      "BGName": 0,
      "BGEffect": 0,
      "PopupFileName": "",
      "ScriptKr": "#wait;1500",
      "VoiceJp": ""
    },
    {
      "TextJp": "[ns] \"ここから先は、私に任せて。\"",
      "TextCn": "[ns]“接下来的事，就交给我吧。”",
      "TextKr": "",
      "TextEn": "[ns] \"I'll take it from here.\"",
      "TextTh": "[ns] \"ต่อจากนี้ปล่อยให้เป็นหน้าที่ของครูเอง\"",
      "TextTw": "[ns]\"接下來，就交給我吧。\"",
      "GroupId": 33170,
      "SelectionGroup": 0,
      "BGMId": 0,
      "Sound": "",
      "Transition": 0,
      "BGName": 0,
      "BGEffect": 0,
      "PopupFileName": "",
      "ScriptKr": "[ns] \"이제 내게 맡겨줘.\"",
      "VoiceJp": ""
    },
    {
      "TextJp": "",
      "TextCn": "",
      "TextKr": "",
      "TextEn": "",
      "TextTh": "",
      "TextTw": "",
      "GroupId": 33170,
      "SelectionGroup": 0,
      "BGMId": 0,
      "Sound": "",
      "Transition": 0,
      "BGName": 0,
      "BGEffect": 0,
      "PopupFileName": "",
      "ScriptKr": "#wait;1500",
      "VoiceJp": ""
    },
    {
      "TextJp": "",
      "TextCn": "",
      "TextKr": "",
      "TextEn": "",
      "TextTh": "",
      "TextTw": "",
      "GroupId": 33170,
      "SelectionGroup": 0,
      "BGMId": 0,
      "Sound": "",
      "Transition": 0,
      "BGName": 0,
      "BGEffect": 0,
      "PopupFileName": "",
      "ScriptKr": "#continued",
      "VoiceJp": ""
    },
    {
      "TextJp": "次回;迷わずに",
      "TextCn": "下一话;不再迷惘",
      "TextKr": "",
      "TextEn": "Next Episode;Without a Moment's Hesitation",
      "TextTh": "ตอนต่อไป;ไม่หวั่นไหว",
      "TextTw": "下一話;毫無迷惘",
      "GroupId": 33170,
      "SelectionGroup": 0,
      "BGMId": 0,
      "Sound": "",
      "Transition": 0,
      "BGName": 4183392339,
      "BGEffect": 0,
      "PopupFileName": "",
      "ScriptKr": "#nextepisode;다음화;흔들리지 않고",
      "VoiceJp": ""
    }
  ]
}